Workbook

Sheet Mode demploi
B2: Imports Lagoon — Fichier de cadrage
B3: Référence commune Lagoon / So'Bloo : un onglet par import, à valider avant tout import de test.
B5: Comment remplir
B6: 1. So'Bloo a pré-rempli ses champs (colonnes bleues) : libellé affiché à l'écran, champ en base, format, obligatoire ou non, règle métier.
B7: 2. Lagoon complète les colonnes jaunes : champ Smile correspondant, à reprendre ou non, obligatoire, règle métier, exemple réel.
B8: 3. Lagoon ajoute en bas de chaque onglet les champs Smile absents de So'Bloo qu'elle souhaite reprendre (Origine = Smile).
B9: 4. Les lignes vertes (Origine = Smile) sont des besoins déjà remontés par Lagoon : champs à créer dans So'Bloo.
B10: 5. Les colonnes Origine, Format, Obligatoire, Règle, À reprendre et Statut sont des listes déroulantes.
B11: 6. Les règles sont revues ensemble en atelier ; le statut passe alors à « Validé ».
B12: Obligatoire = la ligne ne peut pas être importée sans ce champ. Les obligations conditionnelles et les valeurs par défaut sont précisées dans le détail de la règle. Source : code So'Bloo, branche develop du 06/10/2026.
B14: Légende
C15: Colonnes So'Bloo — pré-remplies par So'Bloo
C16: Colonnes Lagoon — à remplir par Lagoon
C17: Champ Smile identifié — à créer dans So'Bloo
B19: Exemple de ligne complétée par Lagoon
B20: Libellé So'Bloo | C20: Champ Smile | D20: À reprendre ? | E20: Obligatoire | F20: Règle Lagoon | G20: Détail de la règle Lagoon
B21: À créer : Accès limité | C21: restricted_access | D21: Oui | E21: Non | F21: Oui | G21: Si Oui : recharges d'achat (Liberté) bloquées en caisse au-delà du plafond. Exemple réel : client 100001
B22: Exemple fictif, pour illustrer le niveau de détail attendu.
B24: Avancement par onglet
B25: Onglet | C25: Lignes | D25: À traiter | E25: En discussion | F25: Validé | G25: Ordre d'import
B26: 1-Comptes comptables | C26: =COUNTA('1-Comptes comptables'!C6:C300) | D26: =COUNTIF('1-Comptes comptables'!R6:R300,"À traiter") | E26: =COUNTIF('1-Comptes comptables'!R6:R300,"En discussion") | F26: =COUNTIF('1-Comptes comptables'!R6:R300,"Validé") | G26: Lot 1
B27: 1b-Familles articles | C27: =COUNTA('1b-Familles articles'!C6:C300) | D27: =COUNTIF('1b-Familles articles'!R6:R300,"À traiter") | E27: =COUNTIF('1b-Familles articles'!R6:R300,"En discussion") | F27: =COUNTIF('1b-Familles articles'!R6:R300,"Validé") | G27: Lot 1
B28: 2-Clients | C28: =COUNTA('2-Clients'!C6:C300) | D28: =COUNTIF('2-Clients'!R6:R300,"À traiter") | E28: =COUNTIF('2-Clients'!R6:R300,"En discussion") | F28: =COUNTIF('2-Clients'!R6:R300,"Validé") | G28: Lot 2
B29: 3-Options articles | C29: =COUNTA('3-Options articles'!C6:C300) | D29: =COUNTIF('3-Options articles'!R6:R300,"À traiter") | E29: =COUNTIF('3-Options articles'!R6:R300,"En discussion") | F29: =COUNTIF('3-Options articles'!R6:R300,"Validé") | G29: Lot 3
B30: 4-Articles | C30: =COUNTA('4-Articles'!C6:C300) | D30: =COUNTIF('4-Articles'!R6:R300,"À traiter") | E30: =COUNTIF('4-Articles'!R6:R300,"En discussion") | F30: =COUNTIF('4-Articles'!R6:R300,"Validé") | G30: Lot 4
B31: 5-Réductions | C31: =COUNTA('5-Réductions'!C6:C300) | D31: =COUNTIF('5-Réductions'!R6:R300,"À traiter") | E31: =COUNTIF('5-Réductions'!R6:R300,"En discussion") | F31: =COUNTIF('5-Réductions'!R6:R300,"Validé") | G31: Lot 5
B32: 6-Abonnements | C32: =COUNTA('6-Abonnements'!C6:C300) | D32: =COUNTIF('6-Abonnements'!R6:R300,"À traiter") | E32: =COUNTIF('6-Abonnements'!R6:R300,"En discussion") | F32: =COUNTIF('6-Abonnements'!R6:R300,"Validé") | G32: Lot 6
B33: 6a-Abo Internet | C33: =COUNTA('6a-Abo Internet'!C6:C300) | D33: =COUNTIF('6a-Abo Internet'!R6:R300,"À traiter") | E33: =COUNTIF('6a-Abo Internet'!R6:R300,"En discussion") | F33: =COUNTIF('6a-Abo Internet'!R6:R300,"Validé") | G33: Lot 6
B34: 6b-Abo VOIP | C34: =COUNTA('6b-Abo VOIP'!C6:C300) | D34: =COUNTIF('6b-Abo VOIP'!R6:R300,"À traiter") | E34: =COUNTIF('6b-Abo VOIP'!R6:R300,"En discussion") | F34: =COUNTIF('6b-Abo VOIP'!R6:R300,"Validé") | G34: Lot 6
B35: Cas limites | C35: =COUNTA('Cas limites'!C6:C300) | D35: =COUNTIF('Cas limites'!H6:H300,"À traiter") | E35: =COUNTIF('Cas limites'!H6:H300,"En discussion") | F35: =COUNTIF('Cas limites'!H6:H300,"Validé") | G35: Tous
B36: Total | C36: =SUM(C26:C35) | D36: =SUM(D26:D35) | E36: =SUM(E26:E35) | F36: =SUM(F26:F35)

Sheet 1-Comptes comptables
A1: Comptes comptables
A2: Comptes généraux et comptes tiers. Importés en premier : familles, articles et clients y font référence. Aucun import autonome n'existe aujourd'hui (les imports actuels créent les comptes manquants avec le code seul) : import à développer.
B4: SO'BLOO — pré-rempli | L4: LAGOON — à compléter | R4: SUIVI COMMUN
A5: N° | B5: Origine | C5: Libellé So'Bloo (écran) | D5: Champ en base (tech) | E5: Description | F5: Format | G5: Valeurs possibles | H5: Obligatoire dans So'Bloo | I5: Règle métier So'Bloo | J5: Détail de la règle So'Bloo | K5: Exemple | L5: Champ Smile correspondant | M5: Champ à reprendre ? | N5: Obligatoire pour Lagoon | O5: Règle métier Lagoon | P5: Détail de la règle Lagoon | Q5: Exemple réel (ID Smile) | R5: Statut | S5: Commentaires
A6: 1 | B6: So'Bloo | C6: Compte général ou compte tiers (non affiché à l'écran) | D6: Choix de la table : general_accounting_account (Général) ou third_party_accounting_account (Tiers) | E6: Compte général ou compte tiers (auxiliaire) | F6: Liste | G6: Compte général / Compte tiers | H6: Oui | I6: Oui | J6: Ce n'est pas un champ mais le type de compte, qui détermine l'écran et la table : un compte général est un compte du plan comptable (7xxx, 44xx, 411 collectif…) ; un compte tiers est un compte auxiliaire individuel (ex. 411DUPONT), rattaché à un compte général via « Compte général associé » | K6: Général | R6: À traiter
A7: 2 | B7: So'Bloo | C7: Code (Comptes généraux / Comptes tiers › fenêtre de création) | D7: general_accounting_account.code ou third_party_accounting_account.code | E7: Numéro du compte | F7: Texte | H7: Oui | I7: Oui | J7: Numéro du compte (ex. 706100, 445710, 411000). Unique par organisation, séparément pour les comptes généraux et les comptes tiers, Y COMPRIS parmi les comptes supprimés (un code supprimé reste bloqué : il faut réactiver le compte). Plan Sage : 7XXX CA, 6XXX charges, 5XXX trésorerie, 44XX TGC, 41XX clients, 1XXX dépôts de garantie | K7: 707100 | R7: À traiter
A8: 3 | B8: So'Bloo | C8: Libellé (Comptes généraux / Comptes tiers › fenêtre de création) | D8: general_accounting_account.label ou third_party_accounting_account.label | E8: Intitulé du compte | F8: Texte | H8: Non | I8: Non | J8: Recommandé. Facultatif à l'écran ; les comptes créés par les imports actuels n'ont pas de libellé | K8: Ventes Internet particuliers | R8: À traiter
A9: 4 | B9: So'Bloo | C9: Type (Comptes généraux › fenêtre de création) | D9: general_accounting_account.type | E9: Usage du compte général | F9: Liste | G9: Clients et comptes rattachés / Clients, effets escomptes non échus / Ventes de produits fabriqués, prestations de services, marchandises / Taxes sur le chiffre d'affaires / Caisse / Banques / Rabais, remises et ristournes accordés par l'entreprise / Pertes / Profits / Fournisseurs / Dépôts de garantie / Débours refacturé | H9: Non | I9: Oui | J9: Obligatoire pour un compte général. Requis à l'écran. Vente, Remise et Débours sont marqués « analytique ». Sert à déterminer le compte par défaut | K9: Vente | R9: À traiter
A10: 5 | B10: So'Bloo | C10: Compte par défaut ? (Comptes généraux › fenêtre de création) | D10: general_accounting_account.is_default | E10: Compte utilisé quand ni l'article ni la famille n'ont de compte | F10: Oui/Non | H10: Non | I10: Oui | J10: Défaut : Non. Un seul compte par défaut par type et par organisation | K10: Non | R10: À traiter
A11: 6 | B11: So'Bloo | C11: Mensualisé ? (XXXXX01, XXXXXX02...) (Comptes généraux › fenêtre de création, visible seulement pour le type Clients, effets escomptes non échus) | D11: general_accounting_account.is_dynamic_per_month | E11: Déclinaison mensuelle du compte | F11: Oui/Non | H11: Non | I11: Oui | J11: Défaut : Non ; uniquement pour le type Clients non échus. Uniquement pour le type Client non échu : génère 12 comptes tiers dont la fin du code = n° du mois | K11: Non | R11: À traiter
A12: 7 | B12: So'Bloo | C12: Compte général associé (Comptes tiers › fenêtre de création) | D12: third_party_accounting_account.general_accounting_account_id | E12: Compte général auquel le compte tiers est rattaché | F12: Code de référence | H12: Non | I12: Oui | J12: Recommandé ; uniquement pour un compte tiers. Relation parent / enfant. Le compte collectif doit exister ou figurer plus haut dans le fichier | K12: 411000 | R12: À traiter
A13: 8 | B13: So'Bloo | C13: Organisation (non affiché à l'écran) | D13: general_accounting_account.organization_id ou third_party_accounting_account.organization_id | E13: Société / BU porteuse du compte | F13: Code de référence | H13: Oui | I13: Oui | J13: Pas de choix à l'écran : c'est l'organisation sélectionnée qui s'applique. Dans le fichier, indiquer l'organisation (Lagoon / Lagoon Business ?) | K13: Lagoon | R13: À traiter
A14: 9 | B14: So'Bloo | C14: Compte supprimé (non affiché à l'écran) | D14: general_accounting_account.is_deleted ou third_party_accounting_account.is_deleted | E14: Compte archivé | F14: Oui/Non | H14: Non | I14: Oui | J14: Défaut : Non. Suppression logique. Suppression refusée si le compte est affecté à un client | K14: Non | R14: À traiter
A15: 10 | B15: Smile | C15: À créer : Catégorie de rapport de vente | D15: À créer | E15: Regroupement Smile des ventes par compte | F15: Liste | I15: Oui | J15: À définir par Lagoon. Aucun équivalent dans So'bloo aujourd'hui (la ventilation passe par la famille). Lien catégorie ↔ compte à préciser par Lagoon | R15: À traiter
A16: 11 | B16: Smile | C16: À créer : Compte général parent | D16: À créer | E16: Double niveau demandé (atelier compta) | F16: Code de référence | I16: Oui | J16: À définir. Développement prévu, non présent dans le code actuel | R16: À traiter
B17: Smile
B18: Smile
B19: Smile
B20: Smile
B21: Smile
B22: Smile
B23: Smile
B24: Smile
B25: Smile
B26: Smile
B27: Smile
B28: Smile
... B31: Smile

Sheet 1b-Familles articles
A1: Familles d'articles
A2: Importées avec le lot 1 : elles portent les taxes et la ventilation comptable par défaut des articles.
B4: SO'BLOO — pré-rempli | L4: LAGOON — à compléter | R4: SUIVI COMMUN
A5: N° | B5: Origine | C5: Libellé So'Bloo (écran) | D5: Champ en base (tech) | E5: Description | F5: Format | G5: Valeurs possibles | H5: Obligatoire dans So'Bloo | I5: Règle métier So'Bloo | J5: Détail de la règle So'Bloo | K5: Exemple | L5: Champ Smile correspondant | M5: Champ à reprendre ? | N5: Obligatoire pour Lagoon | O5: Règle métier Lagoon | P5: Détail de la règle Lagoon | Q5: Exemple réel (ID Smile) | R5: Statut | S5: Commentaires
A6: 1 | B6: So'Bloo | C6: Libellé (Familles d'articles › Informations principales › Description) | D6: tag.label | E6: Nom de la famille | F6: Texte | H6: Oui | I6: Oui | J6: Unique (sans casse) au sein d'une même famille parente | K6: Abonnements Internet | R6: À traiter
A7: 2 | B7: So'Bloo | C7: Code (Familles d'articles › Informations principales › Description) | D7: tag.code | E7: Code unique de la famille | F7: Texte | H7: Oui | I7: Oui | J7: Unique parmi les familles actives. Converti automatiquement en minuscules | K7: abo-int | R7: À traiter
A8: 3 | B8: So'Bloo | C8: Type d’article (Familles d'articles › Informations principales › Description) | D8: tag.article_type | E8: Type proposé aux articles de la famille | F8: Liste | G8: Physique / Service / Abonnement / Débours / Frais / Chèque cadeau | H8: Oui | I8: Oui | J8: Requis à l'écran. Recopié sur l'article à l'import et à la saisie | K8: Abonnement | R8: À traiter
A9: 4 | B9: So'Bloo | C9: Groupe d’unité par défaut (Familles d'articles › Informations principales › Description) | D9: tag.unit_group | E9: Nature de l'unité | F9: Liste | G9: Comptage / Masse / Longueur / Surface / Volume / Temps | H9: Non | I9: Non | J9: Défaut : Comptage (pré-rempli à l'écran). Requis à l'écran | K9: Nombre | R9: À traiter
A10: 5 | B10: So'Bloo | C10: Index (Familles d'articles › Informations principales › Description) | D10: tag.idx | E10: Position dans les listes | F10: Nombre | H10: Non | I10: Non | J10: Requis à l'écran ; défaut proposé : numéro de ligne. Requis à l'écran | K10: 1 | R10: À traiter
A11: 6 | B11: So'Bloo | C11: Parent (Familles d'articles › Informations principales › Description) | D11: tag.parent_id | E11: Famille de niveau supérieur | F11: Code de référence | H11: Non | I11: Oui | J11: Doit exister ou figurer plus haut dans le fichier. Pas de cycle parent / enfant | R11: À traiter
A12: 7 | B12: So'Bloo | C12: Quel est le niveau unique de suivi pour cette famille ? (Familles d'articles › Informations principales, visible avec le module stock et hors type Service) | D12: tag.stock_tracking_type | E12: Suivi par défaut | F12: Liste | G12: Pas de niveau unique / Aucun suivi / Suivi global de l'article / Suivi par lot / Suivi par exemplaire / Suivi par exemplaire avec identification à la vente | H12: Non | I12: Non | J12: Défaut : Pas de niveau unique (vide) ; forcé à Aucun suivi pour Service et à Suivi par exemplaire pour Débours. Recopié une seule fois à la création de l'article (écran et import) ; aucune synchronisation ensuite. Débours impose le suivi par exemplaire | K12: Aucun | R12: À traiter
A13: 8 | B13: So'Bloo | C13: Famille (Paramètres › Taxes › fenêtre d'une taxe › « Associer cette taxe à une famille ») | D13: tax_tag.tax_id + tax_tag.tag_id | E13: Taxes héritées par les articles de la famille | F13: Liste multiple | G13: Taxes paramétrées dans Paramètres › Taxes | H13: Non | I13: Oui | J13: Ne figure pas sur la fiche famille : le lien se fait depuis Paramètres › Taxes (« Associer cette taxe à une famille »). Un article sans taxe propre hérite des taxes de ses familles. Une famille ne peut avoir deux taxes de même code | K13: TGC 22 % | R13: À traiter
A14: 9 | B14: So'Bloo | C14: Compte vente (Familles d'articles › Comptabilité › Comptes) ; « Compte débours » si type Débours | D14: tag_accounting.general_accounting_account_id (type=SALE ou DEBOURS, is_tax_exempt=false, organization_id) | E14: Compte de vente | F14: Code de référence | H14: Non | I14: Oui | J14: Doit exister (onglet 1). Priorité : compte de l'article > compte de la famille la plus fine > compte par défaut du type. ATTENTION : seules les familles directement rattachées à l'article sont lues (pas de remontée vers la famille parente). Pour une famille de type Débours, le champ devient « Compte débours » et les comptes exonéré / remise ne sont pas proposés | K14: 707100 | R14: À traiter
A15: 10 | B15: So'Bloo | C15: Compte vente exonéré (Familles d'articles › Comptabilité › Comptes) | D15: tag_accounting.general_accounting_account_id (type=SALE, is_tax_exempt=true, organization_id) | E15: Compte de vente si client exonéré | F15: Code de référence | H15: Non | I15: Oui | J15: Sans objet pour le type Débours. Utilisé si le devis / l'abonnement est exonéré de taxe | R15: À traiter
A16: 11 | B16: So'Bloo | C16: Compte remise (Familles d'articles › Comptabilité › Comptes) | D16: tag_accounting.general_accounting_account_id (type=DISCOUNT, is_tax_exempt=false, organization_id) | E16: Compte des remises | F16: Code de référence | H16: Non | I16: Oui | J16: Sans objet pour le type Débours. Les comptes de remise ne viennent que de la famille ou du compte par défaut | R16: À traiter
A17: 12 | B17: So'Bloo | C17: Compte remise exonéré (Familles d'articles › Comptabilité › Comptes) | D17: tag_accounting.general_accounting_account_id (type=DISCOUNT, is_tax_exempt=true, organization_id) | E17: Compte des remises, client exonéré | F17: Code de référence | H17: Non | I17: Oui | J17: Sans objet pour le type Débours | R17: À traiter
A18: 13 | B18: So'Bloo | C18: Formule (Familles d'articles › Informations principales › Désignation) | D18: tag.formula_to_create_label | E18: Génère le libellé des articles | F18: Texte | H18: Non | I18: Oui | J18: Si une seule famille porte une formule, le libellé de l'article est recalculé (sauf libellé forcé) | R18: À traiter
A19: 14 | B19: So'Bloo | C19: Gestion de la date de péremption pour les articles de cette famille ? (Familles d'articles › Informations principales › Traçabilité, visible si le paramètre article « date de péremption » est actif) | D19: tag.has_expiration_date | E19: Gestion DLC | F19: Oui/Non | H19: Non | I19: Non | J19: Défaut : Non. Sans objet pour Lagoon | K19: Non | R19: À traiter
B20: Smile
B21: Smile
B22: Smile
B23: Smile
B24: Smile
B25: Smile
B26: Smile
B27: Smile
B28: Smile
B29: Smile
B30: Smile
B31: Smile
... B34: Smile

Sheet 2-Clients
A1: Clients
A2: Particuliers et professionnels. La référence Smile est stockée dans la référence client et sert de clé de rapprochement (clé primaire).
B4: SO'BLOO — pré-rempli | L4: LAGOON — à compléter | R4: SUIVI COMMUN
A5: N° | B5: Origine | C5: Libellé So'Bloo (écran) | D5: Champ en base (tech) | E5: Description | F5: Format | G5: Valeurs possibles | H5: Obligatoire dans So'Bloo | I5: Règle métier So'Bloo | J5: Détail de la règle So'Bloo | K5: Exemple | L5: Champ Smile correspondant | M5: Champ à reprendre ? | N5: Obligatoire pour Lagoon | O5: Règle métier Lagoon | P5: Détail de la règle Lagoon | Q5: Exemple réel (ID Smile) | R5: Statut | S5: Commentaires
A6: 1 | B6: So'Bloo | C6: Réf. (Liste des clients) / « Client <réf> » (en-tête de la fiche client) | D6: customer.ref | E6: Identifiant client Smile (accountUsn) | F6: Code de référence | H6: Oui | I6: Oui | J6: CLÉ PRIMAIRE. Aucune unicité en base : dédoublonnage obligatoire avant import (un doublon casse les imports SEPA et Smile). Si vide, So'bloo génère plus tard C00001 / CF00001 | K6: 100001 | R6: À traiter
A7: 2 | B7: So'Bloo | C7: Type de client (Fiche client › Informations principales) | D7: customer.person_type | E7: Particulier ou professionnel | F7: Liste | G7: Particulier / Société | H7: Oui | I7: Oui | J7: Conditionne les champs obligatoires et les propriétés dynamiques. Particulier : libellé recalculé « Prénom Nom » | K7: Particulier | R7: À traiter
A8: 3 | B8: So'Bloo | C8: Civilité (non affiché à l'écran) | D8: customer.title | E8: M. / Mme | F8: Liste | G8: Monsieur / Madame | H8: Non | I8: Non | K8: Mme | R8: À traiter
A9: 4 | B9: So'Bloo | C9: Nom (Fiche client › Informations principales) | D9: customer.last_name | E9: Nom de famille | F9: Texte | H9: Non | I9: Oui | J9: Obligatoire si particulier. Exigé à l'import et à l'écran pour un particulier | K9: DUPONT | R9: À traiter
A10: 5 | B10: So'Bloo | C10: Prénom (Fiche client › Informations principales) | D10: customer.first_name | E10: Prénom | F10: Texte | H10: Non | I10: Oui | J10: Obligatoire si particulier. Idem | K10: Marie | R10: À traiter
A11: 6 | B11: So'Bloo | C11: Raison sociale (Fiche client › Informations principales) | D11: customer.label | E11: Nom de la société | F11: Texte | H11: Non | I11: Oui | J11: Obligatoire si société. Sert aussi à rattacher les contacts à l'import | K11: SARL EXEMPLE | R11: À traiter
A12: 7 | B12: So'Bloo | C12: Acronyme (Fiche client › Informations principales, société) | D12: customer.acronym | E12: Sigle | F12: Texte | H12: Non | I12: Non | R12: À traiter
A13: 8 | B13: So'Bloo | C13: Forme juridique (Fiche client › Informations principales, société) | D13: customer.legal_status_id | E13: SARL, SAS… | F13: Liste | G13: Référentiel Formes juridiques (paramétrable : SARL, SAS, …) | H13: Non | I13: Oui | J13: L'import actuel crée la valeur si elle est inconnue (attention aux fautes de frappe) | K13: SARL | R13: À traiter
A14: 9 | B14: So'Bloo | C14: Ridet (Fiche client › Informations principales, société) | D14: customer.ridet | E14: Identifiant entreprise NC | F14: Texte | H14: Non | I14: Oui | J14: Obligation paramétrable (société uniquement). Obligatoire pour un pro si le paramétrage du tenant l'exige. Aucun contrôle de format | K14: 1234567.001 | R14: À traiter
A15: 10 | B15: So'Bloo | C15: SIRET (non affiché à l'écran) | D15: customer.siret | E15: Identifiant entreprise métropole | F15: Texte | H15: Non | I15: Oui | J15: UNIQUE en base | R15: À traiter
A16: 11 | B16: So'Bloo | C16: Code APE (non affiché à l'écran) | D16: customer.ape | E16: Code APE | F16: Texte | H16: Non | I16: Non | R16: À traiter
A17: 12 | B17: So'Bloo | C17: Numéro RCS (non affiché à l'écran) | D17: customer.rcs_number | E17: Numéro RCS | F17: Texte | H17: Non | I17: Non | R17: À traiter
A18: 13 | B18: So'Bloo | C18: Ville RCS (non affiché à l'écran) | D18: customer.rcs_city | E18: Ville RCS | F18: Texte | H18: Non | I18: Non | R18: À traiter
A19: 14 | B19: So'Bloo | C19: Capital social (non affiché à l'écran) | D19: customer.social_capital | E19: Capital social | F19: Texte | H19: Non | I19: Non | R19: À traiter
A20: 15 | B20: So'Bloo | C20: Site internet (non affiché à l'écran) | D20: customer.website_url | E20: Site internet | F20: Texte | H20: Non | I20: Non | R20: À traiter
A21: 16 | B21: So'Bloo | C21: Email (Fiche client › Informations principales) | D21: customer.email | E21: Adresse e-mail principale | F21: E-mail | H21: Non | I21: Oui | J21: Obligation paramétrable ; obligatoire si « Coché par défaut comme destinataire facture ». Obligation paramétrable par tenant. Unicité contrôlée à l'écran selon paramétrage, pas à l'import. Aucun contrôle de format côté serveur : à ajouter au contrôle pré-import | K21: client@exemple.nc | R21: À traiter
A22: 17 | B22: So'Bloo | C22: Téléphone (Fiche client › Informations principales) | D22: customer.phone_number | E22: Téléphone fixe | F22: Téléphone | H22: Non | I22: Oui | J22: Obligation paramétrable. Normalisé à l'import : 6 chiffres → +687, 8 → +689, 10 → +33 | K22: 281234 | R22: À traiter
A23: 18 | B23: So'Bloo | C23: Mobile (Fiche client › Informations principales) | D23: customer.mobile_phone_number | E23: Téléphone mobile principal | F23: Téléphone | H23: Non | I23: Oui | J23: Obligation paramétrable. Un seul mobile (voir ligne mobiles multiples) | K23: 771234 | R23: À traiter
A24: 19 | B24: So'Bloo | C24: Date de naissance (Fiche client › Informations principales, particulier) | D24: customer.birth_date | E24: Date de naissance | F24: Date | H24: Non | I24: Oui | J24: Obligation paramétrable (particulier uniquement). Champs existants ; obligation paramétrable par tenant (à confirmer par Lagoon) | R24: À traiter
A25: 20 | B25: So'Bloo | C25: Lieu de naissance (Fiche client › Informations principales, particulier) | D25: customer.place_of_birth | E25: Lieu de naissance | F25: Texte | H25: Non | I25: Oui | J25: Obligation paramétrable (particulier uniquement) | R25: À traiter
A26: 21 | B26: So'Bloo | C26: Carte de fidélité, ou nom du programme de fidélité paramétré (Fiche client › Informations principales) | D26: customer.loyalty_card | E26: N° Conso+ | F26: Texte | H26: Non | I26: Oui | J26: UNIQUE en base | R26: À traiter
A27: 22 | B27: So'Bloo | C27: Badge « Prospect » (en-tête de la fiche client, non modifiable) | D27: customer.is_prospect | E27: Prospect ou client actif | F27: Oui/Non | H27: Non | I27: Oui | J27: Défaut : Oui si le tenant gère les prospects. Forcé à Oui à la création si le tenant gère les prospects : recalcul par batch après import (client actif si abonnement actif ou facture) | K27: Non | R27: À traiter
A28: 23 | B28: So'Bloo | C28: Bloqué (Fiche client › États) | D28: customer_states.blocking_date | E28: Date de blocage | F28: Date | H28: Non | I28: Oui | J28: Par organisation (customer_states.organization_id). Pas de liste de statuts : un état = des dates de blocage, contentieux, suspension. Non couvert par l'import actuel | R28: À traiter
A29: 24 | B29: So'Bloo | C29: Suspendu (Fiche client › États) | D29: customer_states.suspension_date | E29: Date de suspension | F29: Date | H29: Non | I29: Oui | J29: Par organisation | R29: À traiter
A30: 25 | B30: So'Bloo | C30: Contentieux (Fiche client › États) | D30: customer_states.litigation_date | E30: Date de mise en contentieux | F30: Date | H30: Non | I30: Oui | J30: Par organisation | R30: À traiter
A31: 26 | B31: So'Bloo | C31: Groupe de client (Fiche client › Affiliation à un groupe) | D31: customer_to_group.group_id | E31: Association, administration, grand compte, CE, employé… | F31: Liste multiple | G31: Référentiel Groupes de clients (paramétrable) | H31: Non | I31: Oui | J31: Les groupes doivent exister. Servent au moteur de réductions. Non couverts par l'import actuel | K31: EMPLOYE | R31: À traiter
A32: 27 | B32: So'Bloo | C32: « Ce client est associé à … » (en-tête de la fiche client, menu « Ajouter une association avec un client ») ; onglet Établissements du parent | D32: customer.parent_id | E32: Société mère / site | F32: Code de référence | H32: Non | I32: Oui | J32: L'enfant hérite des profils de paiement et des remises du parent. Le parent doit être importé avant | R32: À traiter
A33: 28 | B33: So'Bloo | C33: Adresse ligne 1 (Fiche client › Adresses › Ajouter une adresse) | D33: customer_address.address_line_1 | E33: Adresse ligne 1 | F33: Texte | H33: Non | I33: Non | J33: Obligatoire à l'écran pour toute adresse saisie. Plusieurs adresses possibles, sans type facturation / livraison | K33: 12 rue de l'Exemple | R33: À traiter
A34: 29 | B34: So'Bloo | C34: Adresse ligne 2 (Fiche client › Adresses) | D34: customer_address.address_line_2 | E34: Adresse ligne 2 | F34: Texte | H34: Non | I34: Non | R34: À traiter
A35: 30 | B35: So'Bloo | C35: Complément d'adresse (Fiche client › Adresses) | D35: customer_address.address_supplement | E35: Complément d'adresse | F35: Texte | H35: Non | I35: Non | R35: À traiter
A36: 31 | B36: So'Bloo | C36: Prénom et nom / Entreprise (Fiche client › Adresses) | D36: customer_address.address_label | E36: Destinataire de l'adresse | F36: Texte | H36: Non | I36: Non | J36: Obligatoire à l'écran ; défaut : libellé du client | R36: À traiter
A37: 32 | B37: So'Bloo | C37: Ville (Fiche client › Adresses) | D37: customer_address.city_label | E37: Ville | F37: Texte | H37: Non | I37: Non | J37: Obligatoire si module livraison (référentiel des villes). Libellés libres (pas les référentiels villes / codes postaux) | K37: Nouméa / 98800 | R37: À traiter
A38: 33 | B38: So'Bloo | C38: Code Postal (Fiche client › Adresses) | D38: customer_address.zip_code_label | E38: Code postal | F38: Texte | H38: Non | I38: Non | J38: Obligatoire si module livraison | R38: À traiter
A39: 34 | B39: So'Bloo | C39: Pays (Fiche client › Adresses) | D39: customer_address.country_label | E39: Pays | F39: Texte | H39: Non | I39: Non | R39: À traiter
A40: 35 | B40: So'Bloo | C40: Nom (Fiche client › Contacts › contact) | D40: contact.last_name | E40: Nom du contact | F40: Texte | H40: Non | I40: Oui | J40: Obligatoire pour tout contact importé. E-mail obligatoire si le contact est destinataire des factures. Un contact identique est refusé | R40: À traiter
A41: 36 | B41: So'Bloo | C41: Prénom (Fiche client › Contacts) | D41: contact.first_name | E41: Prénom du contact | F41: Texte | H41: Non | I41: Oui | R41: À traiter
A42: 37 | B42: So'Bloo | C42: Email (Fiche client › Contacts) | D42: contact.email | E42: E-mail du contact | F42: E-mail | H42: Non | I42: Oui | J42: Obligatoire si destinataire facture | R42: À traiter
A43: 38 | B43: So'Bloo | C43: Mobile (Fiche client › Contacts) | D43: contact.mobile_phone_number | E43: Mobile du contact | F43: Téléphone | H43: Non | I43: Oui | R43: À traiter
A44: 39 | B44: So'Bloo | C44: Téléphone (Fiche client › Contacts) | D44: contact.phone_number | E44: Téléphone du contact | F44: Téléphone | H44: Non | I44: Oui | R44: À traiter
A45: 40 | B45: So'Bloo | C45: Fonction (Fiche client › Contacts) | D45: contact.function_id | E45: Fonction du contact | F45: Liste | G45: Référentiel Fonctions (paramétrable) | H45: Non | I45: Oui | R45: À traiter
A46: 41 | B46: So'Bloo | C46: Service (Fiche client › Contacts) | D46: contact.department_id | E46: Service du contact | F46: Liste | G46: Services du client (contacts de type service) | H46: Non | I46: Oui | R46: À traiter
A47: 42 | B47: So'Bloo | C47: Est par défaut coché en tant que destinataire facture (Fiche client › Contacts) | D47: contact.is_invoice_recipient | E47: Contact destinataire des factures | F47: Oui/Non | H47: Non | I47: Oui | J47: Défaut : Non | R47: À traiter
A48: 43 | B48: So'Bloo | C48: Contact avec une procuration (Fiche client › Contacts, contact personne) | D48: contact.is_proxy | E48: Contact avec procuration | F48: Oui/Non | H48: Non | I48: Non | J48: Défaut : Non | R48: À traiter
A49: 44 | B49: So'Bloo | C49: Document de procuration (non affiché à l'écran) | D49: contact.mandate_file_id | E49: Document de procuration | F49: Fichier | H49: Non | I49: Non | R49: À traiter
A50: 45 | B50: So'Bloo | C50: Date de naissance (Fiche client › Contacts, si procuration) | D50: contact.birth_date | E50: Date de naissance du mandataire | F50: Date | H50: Non | I50: Non | J50: Obligatoire si procuration | R50: À traiter
A51: 46 | B51: So'Bloo | C51: Lieu de naissance (Fiche client › Contacts, si procuration) | D51: contact.place_of_birth | E51: Lieu de naissance du mandataire | F51: Texte | H51: Non | I51: Non | J51: Obligatoire si procuration | R51: À traiter
A52: 47 | B52: So'Bloo | C52: Type de profil (Fiche client › Profil de paiement) | D52: payment_profile.type | E52: Comptant / Débit / Débit géré en compta | F52: Liste | G52: Client caisse / Client débit avec paiements / Client débit géré en comptabilité | H52: Non | I52: Oui | J52: Défaut : paramétrage du tenant (Lagoon : Débit). Lagoon : Débit. Un profil par client et par organisation ; l'import applique le même à toutes les organisations | K52: Débit | R52: À traiter
A53: 48 | B53: So'Bloo | C53: Est exonéré de taxe ? (Profil de paiement › Taxes) | D53: payment_profile.is_tax_exempt | E53: Client exonéré de TGC | F53: Oui/Non | H53: Non | I53: Oui | J53: Défaut : Non. Si Oui : mention d'exonération obligatoire ; comptes « exonéré » de la famille utilisés | K53: Non | R53: À traiter
A54: 49 | B54: So'Bloo | C54: Mention franchise de taxe (Profil de paiement › Taxes) | D54: payment_profile.tax_mention_id | E54: Motif légal d'exonération | F54: Liste | G54: Référentiel Mentions de taxe (paramétrable) | H54: Non | I54: Oui | J54: Obligatoire si exonéré. L'import actuel crée la mention si elle est inconnue | R54: À traiter
A55: 50 | B55: So'Bloo | C55: Compte général (Profil de paiement › Comptes comptables) | D55: payment_profile.general_accounting_account_id | E55: Compte collectif client (411…) | F55: Code de référence | H55: Non | I55: Oui | J55: Obligatoire si client débit et si le tenant l'impose ; défaut : compte client par défaut. Obligatoire en profil Débit si le tenant l'impose ; sinon compte client par défaut. Doit exister (onglet 1) | K55: 411000 | R55: À traiter
A56: 51 | B56: So'Bloo | C56: Compte tiers (Profil de paiement › Comptes comptables) | D56: payment_profile.third_party_accounting_account_id | E56: Compte auxiliaire du client | F56: Code de référence | H56: Non | I56: Oui | J56: Obligatoire si client débit et si le tenant l'impose. Même règle. Code unique. L'import actuel le crée s'il est inconnu. Tous les clients Lagoon n'ont pas de compte tiers | R56: À traiter
A57: 52 | B57: So'Bloo | C57: Plafond de débit (Profil de paiement › Client débit, si « Avec un plafond de débit ? » = Oui) | D57: payment_profile.debit_limit_amount | E57: Plafond de débit | F57: Montant | H57: Non | I57: Oui | J57: Obligatoire si plafond activé (profil débit) | R57: À traiter
A58: 53 | B58: So'Bloo | C58: Bloquer la facturation si plafond + marge dépassés ? (Profil de paiement › Client débit) | D58: payment_profile.is_debit_limit_blocking | E58: Plafond bloquant | F58: Oui/Non | H58: Non | I58: Oui | J58: Défaut : Oui dès qu'un plafond est saisi | R58: À traiter
A59: 54 | B59: So'Bloo | C59: Marge du plafond (Profil de paiement › Client débit) | D59: payment_profile.debit_limit_margin | E59: Marge du plafond | F59: Pourcentage | H59: Non | I59: Oui | R59: À traiter
A60: 55 | B60: So'Bloo | C60: Délai de règlement (Profil de paiement › Client débit) | D60: payment_profile.settlement_period | E60: En jours | F60: Nombre | H60: Non | I60: Non | J60: Défaut : 1 (mois). En MOIS (défaut 1 mois), pas en jours : convertir les délais Smile | K60: 30 | R60: À traiter
A61: 56 | B61: So'Bloo | C61: Type de paiement privilégié (Profil de paiement › Paiement) | D61: payment_profile.preferred_payment_type | E61: Prélèvement, virement, espèces, carte… | F61: Liste | G61: Selon le paramétrage du tenant, parmi : Espèce / Chèque / Virement / Prélèvement / Carte bancaire / … | H61: Non | I61: Oui | J61: Forcé à Prélèvement par la migration des mandats | K61: Prélèvement | R61: À traiter
A62: 57 | B62: So'Bloo | C62: Nom de la banque (Profil de paiement › Informations RIB) | D62: bank_information.bank_name | E62: Nom de la banque | F62: Texte | H62: Non | I62: Oui | J62: Obligatoire si prélèvement automatique. Exigé à l'écran si le prélèvement est actif. Pros en BCI, particuliers en BNC (atelier 17) | K62: BNC | R62: À traiter
A63: 58 | B63: So'Bloo | C63: Code banque (Profil de paiement › Informations RIB) | D63: bank_account.bank_code | E63: Code banque | F63: Texte | H63: Non | I63: Oui | J63: Obligatoire si prélèvement (5 chiffres). Clé RIB contrôlée (modulo 97). L'IBAN est calculé à partir du RIB (pays forcé FR, à vérifier pour la NC) ; pas de champ BIC. RIB ≠ 23 caractères = rejet SEPA | K63: 14889 00001 12345678901 23 | R63: À traiter
A64: 59 | B64: So'Bloo | C64: Code guichet (Profil de paiement › Informations RIB) | D64: bank_account.office_code | E64: Code guichet | F64: Texte | H64: Non | I64: Oui | J64: Obligatoire si prélèvement (5 chiffres) | R64: À traiter
A65: 60 | B65: So'Bloo | C65: Numéro de compte (Profil de paiement › Informations RIB) | D65: bank_account.account_number | E65: Numéro de compte | F65: Texte | H65: Non | I65: Oui | J65: Obligatoire si prélèvement (11 caractères) | R65: À traiter
A66: 61 | B66: So'Bloo | C66: Clé RIB (Profil de paiement › Informations RIB) | D66: bank_account.rib_key | E66: Clé RIB | F66: Texte | H66: Non | I66: Oui | J66: Obligatoire si prélèvement (2 chiffres, contrôle modulo 97) | R66: À traiter
A67: 62 | B67: So'Bloo | C67: Titulaire du compte (Profil de paiement › Informations RIB) | D67: bank_account.account_name | E67: Nom du débiteur | F67: Texte | H67: Non | I67: Oui | J67: Défaut : libellé du client. Nom du débiteur SEPA (libellé client sinon). Non appliqué par la migration actuelle des mandats | R67: À traiter
A68: 63 | B68: So'Bloo | C68: RUM (généré) (Profil de paiement › Prélèvement automatique, lecture seule) ; colonne RUM (Prélèvements › Mandat) | D68: direct_debit_property.rum | E68: Mandat SEPA | F68: Texte | H68: Non | I68: Oui | J68: Défaut : générée si vide (35 caractères max.). Générée si vide (préfixe organisation + ids). À reprendre de Smile si elle existe, pour la continuité des prélèvements | R68: À traiter
A69: 64 | B69: So'Bloo | C69: Date signature (Prélèvements › Mandat) / Date de signature (action « Joindre le mandat signé ») | D69: direct_debit_property.signature_date | E69: Mandat SEPA | F69: Date | H69: Non | I69: Oui | J69: Obligatoire si prélèvement (mandat Validé). Absente de la migration actuelle des mandats : à ajouter | R69: À traiter
A70: 65 | B70: So'Bloo | C70: Statut (Prélèvements › Mandat) | D70: direct_debit_property.status | E70: Brouillon / Validé / Annulé | F70: Liste | G70: Brouillon / Validé / Annulé | H70: Non | I70: Oui | J70: Obligatoire si prélèvement. Seuls les mandats Validés sont prélevés. Mandat désactivé automatiquement après 36 mois sans prélèvement | K70: Validé | R70: À traiter
A71: 66 | B71: So'Bloo | C71: Titre (Fiche client › Notes du client › Ajouter) | D71: customer_comment.title | E71: Titre de la note | F71: Texte | H71: Non | I71: Non | J71: Non couvertes par l'import actuel | R71: À traiter
A72: 67 | B72: So'Bloo | C72: Commentaire (Fiche client › Notes du client) | D72: customer_comment.comment | E72: Contenu de la note | F72: Texte | H72: Non | I72: Non | R72: À traiter
A73: 68 | B73: So'Bloo | C73: Épingler cette note (Fiche client › Notes du client) | D73: customer_comment.is_pinned | E73: Note épinglée | F73: Oui/Non | H73: Non | I73: Non | J73: Défaut : Non | R73: À traiter
A74: 69 | B74: So'Bloo | C74: Libellé propre à chaque propriété (Fiche client › Informations principales, sous les champs standards) | D74: customer_attribute.value (+ customer_attribute_value pour les listes) | E74: Champs personnalisés propres à Particulier / Professionnel | F74: Texte | H74: Non | I74: Oui | J74: Obligation paramétrable par propriété et par type de client. Ni import ni contrôle serveur aujourd'hui : développement ou chargement SQL nécessaire | R74: À traiter
A75: 70 | B75: So'Bloo | C75: Groupe (Fiche client › Informations principales, société) | D75: customer.company_group | E75: Groupe (société) | F75: Texte | H75: Non | I75: Oui | R75: À traiter
A76: 71 | B76: So'Bloo | C76: Activité (Fiche client › Informations principales) | D76: customer.occupation | E76: Activité | F76: Texte | H76: Non | I76: Oui | J76: Obligation paramétrable | R76: À traiter
A77: 72 | B77: So'Bloo | C77: Fax (Fiche client › Informations principales) | D77: customer.fax | E77: Fax | F77: Téléphone | H77: Non | I77: Oui | J77: Obligation paramétrable | R77: À traiter
A78: 73 | B78: So'Bloo | C78: Hors territoire (Fiche client › Informations principales) | D78: customer.out_of_territory | E78: Hors territoire | F78: Oui/Non | H78: Non | I78: Oui | J78: Défaut : Non | R78: À traiter
A79: 74 | B79: So'Bloo | C79: Pays (Fiche client › Informations principales, si hors territoire) | D79: customer.country_code / customer.country_label | E79: Pays du client hors territoire | F79: Liste | G79: Référentiel douanier des pays | H79: Non | I79: Oui | J79: Obligatoire si hors territoire | R79: À traiter
A80: 75 | B80: So'Bloo | C80: Coché par défaut comme destinataire facture (Fiche client › Informations principales) | D80: customer.is_invoice_recipient | E80: E-mail client destinataire des factures | F80: Oui/Non | H80: Non | I80: Oui | R80: À traiter
A81: 76 | B81: So'Bloo | C81: Envoyer son récapitulatif tous les mois (Fiche client › Informations principales) | D81: customer.send_invoice_summary_monthly | E81: Récapitulatif mensuel | F81: Oui/Non | H81: Non | I81: Oui | J81: Défaut : Non | R81: À traiter
A82: 77 | B82: So'Bloo | C82: « Modifier le profil de paiement pour <organisation> » (Fiche client › Profil de paiement) | D82: payment_profile.organization_id | E82: Organisation du profil de paiement | F82: Liste | G82: Lagoon / Lagoon Business | H82: Non | I82: Oui | J82: Défaut : profil identique pour toutes les organisations (import actuel) | R82: À traiter
A83: 78 | B83: So'Bloo | C83: Prélèvement automatique? (Profil de paiement › Prélèvement automatique, lecture seule) | D83: direct_debit_property.has_direct_debit | E83: Prélèvement automatique actif | F83: Oui/Non | H83: Non | I83: Oui | J83: Défaut : Non | R83: À traiter
A84: 79 | B84: So'Bloo | C84: Autoriser le paiement différé ? (Profil de paiement › Prélèvement automatique) | D84: payment_profile.deferred_payment | E84: Paiement différé autorisé | F84: Oui/Non | H84: Non | I84: Oui | J84: Défaut : Oui | R84: À traiter
A85: 80 | B85: So'Bloo | C85: Bon de commande requis? (Profil de paiement › Bon de commande) | D85: payment_profile.is_purchase_order_required | E85: Bon de commande requis | F85: Oui/Non | H85: Non | I85: Oui | J85: Défaut : Non. Champ visible absent du cadrage (utile pour les administrations). | R85: À traiter
A86: 81 | B86: So'Bloo | C86: Inclure dans les envois en masse et auto des factures ? (Profil de paiement › Envoi) | D86: payment_profile.include_in_mass_invoice_sending | E86: Inclus dans les envois de factures en masse | F86: Oui/Non | H86: Non | I86: Oui | J86: Défaut : Oui | R86: À traiter
A87: 82 | B87: So'Bloo | C87: Devise pour devis et facture (Profil de paiement › Devise par défaut) | D87: payment_profile.default_currency | E87: Devise par défaut | F87: Liste | G87: XPF / EUR | H87: Non | I87: Oui | J87: Défaut : devise du tenant | R87: À traiter
A88: 83 | B88: So'Bloo | C88: Justifcatif d'exonération (Profil de paiement › Taxes, si exonéré) | D88: payment_profile.tax_exempt_proof_file_id | E88: Justificatif d'exonération | F88: Fichier | H88: Non | I88: Oui | R88: À traiter
A89: 84 | B89: So'Bloo | C89: PDF RIB (Profil de paiement › Informations RIB) | D89: bank_account.rib_file_id | E89: RIB (PDF) | F89: Fichier | H89: Non | I89: Oui | R89: À traiter
A90: 85 | B90: So'Bloo | C90: Bordereau de prélèvement automatique signé (Profil de paiement › Prélèvement automatique) | D90: direct_debit_form (lié à direct_debit_property) | E90: Mandat de prélèvement signé | F90: Fichier | H90: Non | I90: Oui | R90: À traiter
A91: 86 | B91: Smile | C91: À créer : Téléphones mobiles supplémentaires | D91: À créer | E91: Plusieurs mobiles par client | F91: Téléphone | I91: Oui | J91: Via propriété dynamique ou contacts ; nombre maximum à définir | R91: À traiter
A92: 87 | B92: Smile | C92: À créer : Accès limité | D92: À créer | E92: Restriction des recharges d'achat (Liberté…) | F92: Oui/Non | I92: Oui | J92: Probablement une propriété dynamique. Effets de l'indicateur à décrire par Lagoon | R92: À traiter
A93: 88 | B93: Smile | C93: À créer : Client Chorus | D93: À créer | E93: Administration facturée via Chorus | F93: Oui/Non | I93: Oui | J93: Si Oui, e-mail non obligatoire | R93: À traiter
B94: Smile
B95: Smile
B96: Smile
B97: Smile
B98: Smile
B99: Smile
B100: Smile
B101: Smile
...

Sheet 3-Options articles
A1: Options d'articles
A2: Importées avant les articles standards. Dans So'bloo, une option est un article (avec sa déclinaison et son prix) rattaché à l'article principal via un groupe d'options.
B4: SO'BLOO — pré-rempli | L4: LAGOON — à compléter | R4: SUIVI COMMUN
A5: N° | B5: Origine | C5: Libellé So'Bloo (écran) | D5: Champ en base (tech) | E5: Description | F5: Format | G5: Valeurs possibles | H5: Obligatoire dans So'Bloo | I5: Règle métier So'Bloo | J5: Détail de la règle So'Bloo | K5: Exemple | L5: Champ Smile correspondant | M5: Champ à reprendre ? | N5: Obligatoire pour Lagoon | O5: Règle métier Lagoon | P5: Détail de la règle Lagoon | Q5: Exemple réel (ID Smile) | R5: Statut | S5: Commentaires
A6: 1 | B6: So'Bloo | C6: Code article (Fiche article › Informations principales › Principales ; visible si le tenant a l'option « code article ») | D6: variant.code | E6: Code unique de l'option | F6: Texte | H6: Oui | I6: Oui | J6: CLÉ DE RAPPROCHEMENT. Unique sans casse parmi les déclinaisons actives (contrainte en base) | K6: OPT-IP-FIXE | R6: À traiter
A7: 2 | B7: So'Bloo | C7: Désignation (Fiche article › Informations principales › Principales) | D7: article.label + variant.label | E7: Nom de l'option | F7: Texte | H7: Oui | I7: Oui | J7: Seul champ bloquant de l'import Excel actuel | K7: Adresse IP fixe | R7: À traiter
A8: 3 | B8: So'Bloo | C8: Description (Fiche article › Informations principales › Principales) | D8: article.description | E8: Texte descriptif | F8: Texte | H8: Non | I8: Non | R8: À traiter
A9: 4 | B9: So'Bloo | C9: Type d'article (non affiché à l'écran) | D9: article.type | E9: Nature de l'option | F9: Liste | G9: Physique / Service / Abonnement / Débours / Frais / Chèque cadeau | H9: Non | I9: Oui | J9: Défaut : type de la famille. Débours impose un suivi par exemplaire | K9: Service | R9: À traiter
A10: 5 | B10: So'Bloo | C10: Famille (Fiche article › Informations principales › Principales ; ou étape « Quelle est la famille d’article ? » à la création si module stock) | D10: article_tag.tag_id (article_tag.article_id, idx=0) | E10: Famille d'articles | F10: Code de référence | H10: Non | I10: Oui | J10: Obligatoire si le paramètre tenant « famille obligatoire » (tagRequired) est actif. Doit exister (onglet 1b). Obligatoire si le paramètre tenant « famille obligatoire » est actif | K10: abo-int | R10: À traiter
A11: 6 | B11: So'Bloo | C11: Est une option (non affiché à l'écran) | D11: article.is_option | E11: L'article peut être proposé en option | F11: Oui/Non | H11: Non | I11: Oui | J11: Défaut : Non ; passe à Oui quand l'article est ajouté dans un groupe d'options. Positionné automatiquement quand l'article est ajouté à un groupe d'options (et retiré à sa suppression). En import direct, aucune valeur par défaut : envoyer Oui pour une option, Non sinon | K11: Oui | R11: À traiter
A12: 7 | B12: So'Bloo | C12: Disponiblité de l’article (Fiche article › Informations principales ; section visible selon le paramétrage des champs) | D12: article.is_option_only | E12: Ne se vend pas seul | F12: Liste | G12: Cet article est disponible en tant qu'article principal / Cet article est seulement disponible en tant qu'option | H12: Non | I12: Oui | J12: Défaut : article principal (Non). Champ non nul sans valeur par défaut : à fournir | K12: Oui | R12: À traiter
A13: 8 | B13: So'Bloo | C13: Type de prix (non affiché à l'écran) | D13: transaction_price.type | E13: Vente, abonnement ou package | F13: Liste | G13: Vente / Abonnement / Package | H13: Non | I13: Oui | J13: Défaut : Vente ; un seul prix par type (et par site). Un seul prix global par type | K13: Abonnement | R13: À traiter
A14: 9 | B14: So'Bloo | C14: Prix unitaire HT, ou Prix unitaire TTC selon la « Préférence de saisie de prix » (Fiche article › Tarification › Dernier prix en …) | D14: transaction_price.price_value (+ price_including_taxes_value si saisie TTC) | E14: Prix unitaire HT | F14: Montant | H14: Non | I14: Oui | J14: Obligatoire sauf si Prix libre = Oui. Montant et devise obligatoires. Saisie TTC possible | K14: 1000 | R14: À traiter
A15: 10 | B15: So'Bloo | C15: Devise (non affiché à l'écran) | D15: transaction_price.price_currency | E15: Devise du prix | F15: Code de référence | H15: Non | I15: Non | J15: Défaut : XPF. XPF | K15: XPF | R15: À traiter
A16: 11 | B16: So'Bloo | C16: Fréquence de facturation (Fiche article › Tarification › Dernier prix en abonnement) | D16: transaction_price.invoice_frequency_multiple + transaction_price.invoice_frequency_period | E16: Multiple + période (jour, semaine, mois, année) | F16: Liste | G16: 1 / 2 / 3 / 4 / 5 / 6 × mois / ans | H16: Non | I16: Oui | J16: Obligatoire si prix Abonnement. Non contrôlé par le serveur : à exiger à l'import pour un prix Abonnement | K16: 1 mois | R16: À traiter
A17: 12 | B17: So'Bloo | C17: Taxes (Fiche article › Tarification › Taxes, via « Cliquer ici pour modifier les taxes pour cet article ») | D17: article_tax.tax_id (article_tax.article_id) | E17: Taxes propres à l'option | F17: Liste multiple | G17: Taxes paramétrées dans Paramètres › Taxes | H17: Non | I17: Oui | J17: Défaut : taxes héritées de la famille. Si renseignées, remplacent totalement celles de la famille | R17: À traiter
A18: 13 | B18: So'Bloo | C18: Compte général (Fiche article › Comptabilité › Comptabilité ; visible avec le droit Comptabilité) | D18: article_accounting.general_accounting_account_id (article_accounting.article_id, organization_id) | E18: Surcharge du compte de la famille | F18: Code de référence | H18: Non | I18: Oui | J18: Défaut : compte de la famille. Prioritaire sur la famille, y compris pour un client exonéré | R18: À traiter
A19: 14 | B19: So'Bloo | C19: Actif (Fiche article › fenêtre de création › Principales) ; ensuite action « Supprimer » | D19: article.is_deleted (+ variant.is_deleted) | E19: Option obsolète | F19: Oui/Non | H19: Non | I19: Oui | J19: Défaut : actif (is_deleted = Non). Une option obsolète encore utilisée par un abonnement doit être importée | K19: Non | R19: À traiter
A20: 15 | B20: So'Bloo | C20: Quel niveau de suivi souhaitez-vous mettre en place ? (fenêtre de création d'article) | D20: article.with_stock_tracking + article.is_lot_tracked + article.is_single_tracked + article.is_single_tracked_on_sale | E20: Niveau de suivi de stock | F20: Liste | G20: Non, je ne gère pas le stock / Suivi global de l'article / Suivi par lot / Suivi par exemplaire / Suivi par exemplaire avec identification à la vente | H20: Non | I20: Oui | J20: Défaut : niveau de la famille, sinon aucun suivi | R20: À traiter
A21: 16 | B21: So'Bloo | C21: Unité de vente (Fiche article › Informations principales) | D21: variant.article_unit_reference_id | E21: Unité de vente | F21: Liste | G21: Unités paramétrées (selon le groupe d'unité) | H21: Non | I21: Oui | J21: Défaut : unité par défaut du groupe | R21: À traiter
A22: 17 | B22: So'Bloo | C22: Prix libre (Fiche article › Tarification › Dernier prix en …) | D22: transaction_price.is_open_price | E22: Prix libre | F22: Oui/Non | H22: Non | I22: Oui | J22: Défaut : Non | R22: À traiter
A23: 18 | B23: So'Bloo | C23: Préférence de saisie de prix (Fiche article › Tarification › Dernier prix en …) | D23: transaction_price.is_input_with_tax_included | E23: Préférence de saisie de prix | F23: Liste | G23: HT / TTC | H23: Non | I23: Oui | J23: Défaut : HT | R23: À traiter
A24: 19 | B24: So'Bloo | C24: Coût unitaire HT (Fiche article › Tarification › Coût unitaire / Coût de la prestation) | D24: variant.cost_value + variant.cost_currency | E24: Coût d'achat unitaire HT | F24: Montant | H24: Non | I24: Oui | J24: Requis à l'écran si non suivi en stock (défaut 0) | R24: À traiter
A25: 20 | B25: Smile | C25: À créer : Code variante | D25: À créer | E25: Si Lagoon utilise les variantes | F25: Texte | I25: Oui | J25: Si Lagoon utilise les variantes. Les variantes existent déjà dans So'Bloo (onglet « Variants » de la fiche article, si l'option est activée sur le tenant) : chaque variante a son propre code article. Choix de modélisation à faire avec Lagoon | R25: À traiter
A26: 21 | B26: Smile | C26: À créer : Dépendances entre options | D26: À créer | E26: Options obligatoires ou incompatibles | F26: Code de référence | I26: Oui | J26: À décrire par Lagoon. En partie couvert par les groupes d'options : « Type de sélection : Unique » rend les options d'un groupe incompatibles, « Une des options est obligatoire » rend le choix obligatoire. Seules les dépendances entre groupes seraient à créer | R26: À traiter
B27: Smile
B28: Smile
B29: Smile
B30: Smile
B31: Smile
B32: Smile
B33: Smile
B34: Smile
B35: Smile
B36: Smile
B37: Smile
B38: Smile
... B41: Smile

Sheet 4-Articles
A1: Articles standards
A2: Rattachés à leurs options. Comprend les frais fixes (mise en service, installation…). Une ligne = un article + sa déclinaison + son prix.
B4: SO'BLOO — pré-rempli | L4: LAGOON — à compléter | R4: SUIVI COMMUN
A5: N° | B5: Origine | C5: Libellé So'Bloo (écran) | D5: Champ en base (tech) | E5: Description | F5: Format | G5: Valeurs possibles | H5: Obligatoire dans So'Bloo | I5: Règle métier So'Bloo | J5: Détail de la règle So'Bloo | K5: Exemple | L5: Champ Smile correspondant | M5: Champ à reprendre ? | N5: Obligatoire pour Lagoon | O5: Règle métier Lagoon | P5: Détail de la règle Lagoon | Q5: Exemple réel (ID Smile) | R5: Statut | S5: Commentaires
A6: 1 | B6: So'Bloo | C6: Code article (Fiche article › Informations principales › Principales ; visible si le tenant a l'option « code article ») | D6: variant.code | E6: Code unique de l'article | F6: Texte | H6: Oui | I6: Oui | J6: CLÉ DE RAPPROCHEMENT. Unique sans casse parmi les déclinaisons actives. L'import actuel ne fait que créer (pas de mise à jour) : à faire évoluer pour le rejeu | K6: ALTO-PLUS | R6: À traiter
A7: 2 | B7: So'Bloo | C7: Désignation (Fiche article › Informations principales › Principales) | D7: article.label + variant.label | E7: Nom de l'article | F7: Texte | H7: Oui | I7: Oui | J7: Seul champ bloquant de l'import actuel ; libellé de déclinaison obligatoire | K7: Forfait Internet Alto+ | R7: À traiter
A8: 3 | B8: So'Bloo | C8: Description (Fiche article › Informations principales › Principales) ; « Conditions d’utilisation » pour un chèque cadeau | D8: article.description | E8: Texte descriptif | F8: Texte | H8: Non | I8: Non | R8: À traiter
A9: 4 | B9: So'Bloo | C9: Type d'article (non affiché à l'écran) | D9: article.type | E9: Nature de l'article | F9: Liste | G9: Physique / Service / Abonnement / Débours / Frais / Chèque cadeau | H9: Non | I9: Oui | J9: Défaut : type de la famille. À l'import, remplacé par le type de la famille. Débours impose un suivi par exemplaire | K9: Abonnement | R9: À traiter
A10: 5 | B10: So'Bloo | C10: Famille (Fiche article › Informations principales › Principales ; ou étape « Quelle est la famille d’article ? » à la création si module stock) | D10: article_tag.tag_id (article_tag.article_id, idx) | E10: Famille(s) d'articles | F10: Code de référence | H10: Non | I10: Oui | J10: Obligatoire si le paramètre tenant « famille obligatoire » est actif. Doit exister (onglet 1b). Plusieurs familles possibles ; la plus fine l'emporte pour la ventilation | K10: abo-int | R10: À traiter
A11: 6 | B11: So'Bloo | C11: Réf. externe (Fiche article › Informations principales › Principales ; visible pour un article Physique et seulement si le module Commandes fournisseurs est absent) | D11: variant.external_ref | E11: Référence fournisseur | F11: Texte | H11: Non | I11: Oui | J11: Ce n'est pas la référence fournisseur (voir onglet Fournisseurs). Unique sans casse. Masqué si le module Commandes fournisseurs est actif | R11: À traiter
A12: 7 | B12: So'Bloo | C12: Quel niveau de suivi souhaitez-vous mettre en place ? (fenêtre de création d'article) ; affiché ensuite en lecture seule dans « Suivi de l’article » (Informations principales) | D12: article.with_stock_tracking + article.is_lot_tracked + article.is_single_tracked + article.is_single_tracked_on_sale | E12: Aucun, global, par lot, par exemplaire | F12: Liste | G12: Non, je ne gère pas le stock / Suivi global de l'article / Suivi par lot / Suivi par exemplaire / Suivi par exemplaire avec identification à la vente | H12: Non | I12: Oui | J12: Défaut : niveau de la famille, sinon aucun suivi. Champs non nuls. Matériel (modem, routeur) suivi par exemplaire ; services non suivis. Non modifiable une fois des exemplaires créés | K12: Aucun | R12: À traiter
A13: 8 | B13: So'Bloo | C13: Coût unitaire HT (Fiche article › Tarification › Coût unitaire ; « Coût de la prestation » pour un service) | D13: variant.cost_value + variant.cost_currency | E13: Coût unitaire | F13: Montant | H13: Non | I13: Oui | J13: Requis à l'écran si l'article n'est pas suivi en stock (défaut 0). Ignoré si l'article est suivi en stock (coût issu des achats) | R13: À traiter
A14: 9 | B14: So'Bloo | C14: Fournisseur (Fiche article › Fournisseurs › Fournisseurs associés › Ajouter un article fournisseur) | D14: variant_supplier.supplier_id (variant_supplier.variant_id) | E14: Fournisseur principal | F14: Code de référence | H14: Non | I14: Oui | J14: Fournisseurs de l'article (plusieurs possibles), avec « Code article fournisseur » et « Désignation fournisseur » requis. Le fournisseur doit exister | R14: À traiter
A15: 10 | B15: So'Bloo | C15: Type de prix (non affiché à l'écran) | D15: transaction_price.type | E15: Vente, abonnement ou package | F15: Liste | G15: Vente / Abonnement / Package | H15: Non | I15: Oui | J15: Défaut : Vente ; un seul prix par type (et par site). Un seul prix global par type (et par entrepôt). Cas Alto+ : vendu uniquement en abonnement, sans prix de vente (problème ouvert) | K15: Abonnement | R15: À traiter
A16: 11 | B16: So'Bloo | C16: Prix unitaire HT, ou Prix unitaire TTC selon la « Préférence de saisie de prix » (Fiche article › Tarification › Dernier prix en …) | D16: transaction_price.price_value (+ price_including_taxes_value si saisie TTC) | E16: Prix unitaire HT | F16: Montant | H16: Non | I16: Oui | J16: Obligatoire sauf si Prix libre = Oui. Montant et devise obligatoires. Saisie TTC possible (HT recalculé). L'import actuel met 0 si vide | K16: 5000 | R16: À traiter
A17: 12 | B17: So'Bloo | C17: Devise (non affiché à l'écran) | D17: transaction_price.price_currency | E17: Devise du prix | F17: Code de référence | H17: Non | I17: Non | J17: Défaut : XPF | K17: XPF | R17: À traiter
A18: 13 | B18: So'Bloo | C18: Fréquence de facturation (Fiche article › Tarification › Dernier prix en abonnement) | D18: transaction_price.invoice_frequency_multiple + transaction_price.invoice_frequency_period | E18: Multiple + période + jour | F18: Liste | G18: 1 / 2 / 3 / 4 / 5 / 6 × mois / ans | H18: Non | I18: Oui | J18: Obligatoire si prix Abonnement. Non contrôlé par le serveur : à exiger à l'import pour un prix Abonnement. Deux prix d'une même commande s'additionnent seulement à fréquence égale | K18: 1 mois, le 1er | R18: À traiter
A19: 14 | B19: So'Bloo | C19: Prix libre (Fiche article › Tarification › Dernier prix en …) | D19: transaction_price.is_open_price | E19: Prix saisi à la vente | F19: Oui/Non | H19: Non | I19: Oui | J19: Défaut : Non ; impossible pour un débours. Si Non, un prix est exigé à l'écran | K19: Non | R19: À traiter
A20: 15 | B20: So'Bloo | C20: Éco-participation (Fiche article › Tarification › Dernier prix en vente) | D20: transaction_price.eco_contribution_id | E20: Éco-contribution rattachée | F20: Code de référence | H20: Non | I20: Oui | J20: Uniquement sur un prix Vente, avec les mêmes taxes que l'article | R20: À traiter
A21: 16 | B21: So'Bloo | C21: Taxes (Fiche article › Tarification › Taxes, via « Cliquer ici pour modifier les taxes pour cet article ») | D21: article_tax.tax_id (article_tax.article_id) | E21: Taxes propres à l'article | F21: Liste multiple | G21: Taxes paramétrées dans Paramètres › Taxes | H21: Non | I21: Oui | J21: Défaut : taxes héritées de la famille. Si renseignées, remplacent totalement celles de la famille ; sinon héritage | K21: TGC 22 % | R21: À traiter
A22: 17 | B22: So'Bloo | C22: Unité de vente (Fiche article › Informations principales ; affichée seulement si le groupe d'unité compte au moins 2 unités) | D22: variant.article_unit_reference_id | E22: Unité de vente | F22: Liste | G22: Unités paramétrées dans Paramètres › Unités (selon le groupe d'unité de la famille) | H22: Non | I22: Oui | J22: Défaut : unité par défaut du groupe. Unité par défaut du tenant si vide ; requise à l'écran | K22: Unité | R22: À traiter
A23: 18 | B23: So'Bloo | C23: Compte général (Fiche article › Comptabilité › Comptabilité ; visible avec le droit Comptabilité) | D23: article_accounting.general_accounting_account_id (article_accounting.article_id, organization_id) | E23: Surcharge du compte de la famille | F23: Code de référence | H23: Non | I23: Oui | J23: Défaut : compte de la famille. Prioritaire sur la famille, y compris client exonéré. Un compte par forfait demandé par Lagoon. Modification réservée aux droits Comptabilité | K23: 706100 | R23: À traiter
A24: 19 | B24: So'Bloo | C24: A des options (non affiché à l'écran) | D24: article.has_option | E24: L'article propose des options | F24: Oui/Non | H24: Non | I24: Oui | J24: Défaut : Non. Recalculé par le serveur seulement via l'écran : à positionner à l'import direct | K24: Oui | R24: À traiter
A25: 20 | B25: So'Bloo | C25: A une option obligatoire (non affiché à l'écran) | D25: article.has_option_required | E25: Une option doit être choisie | F25: Oui/Non | H25: Non | I25: Oui | J25: Défaut : Non. Idem | K25: Non | R25: À traiter
A26: 21 | B26: So'Bloo | C26: Nom du groupe (Fiche article › Options) | D26: option_group.label | E26: Nom du groupe d'options | F26: Texte | H26: Non | I26: Oui | J26: Obligatoire si l'article a des options | K26: Services complémentaires | R26: À traiter
A27: 22 | B27: So'Bloo | C27: Type de sélection pour les options (Fiche article › Options) | D27: option_group.is_unique | E27: Choix d'une seule ou de plusieurs options du groupe | F27: Liste | G27: Multiple / Unique | H27: Non | I27: Oui | J27: Défaut : Multiple. Unique = options du groupe incompatibles entre elles | K27: Unique | R27: À traiter
A28: 23 | B28: So'Bloo | C28: Une des options est obligatoire (Fiche article › Options) | D28: option_group.is_required | E28: Le client doit choisir une option du groupe | F28: Oui/Non | H28: Non | I28: Oui | J28: Proposé uniquement pour un groupe Unique. Défaut : Non | K28: Non | R28: À traiter
A29: 24 | B29: So'Bloo | C29: Sélection de l'article ou du service + Prix + « La quantité est obligatoirement égale à l’article » (Fiche article › Options › fenêtre Option) | D29: option.variant_id + option.transaction_price_id + option.is_quantity_from_parent (option.group_id) | E29: Codes des options du groupe | F29: Code de référence | H29: Non | I29: Oui | J29: Obligatoire si l'article a des options. Chaque option doit exister (onglet 3) et porte son propre prix dans le groupe. Quantité éventuellement reprise du parent | K29: OPT-IP-FIXE;OPT-HOTLINE | R29: À traiter
A30: 25 | B30: So'Bloo | C30: Garantie (Fiche article › Informations principales › Principales ; articles Physiques uniquement) | D30: article.guarantee | E30: Durée de garantie | F30: Nombre | H30: Non | I30: Non | R30: À traiter
A31: 26 | B31: So'Bloo | C31: Actif (Fiche article › fenêtre de création › Principales) ; ensuite action « Supprimer » | D31: article.is_deleted (+ variant.is_deleted) | E31: Article obsolète | F31: Oui/Non | H31: Non | I31: Oui | J31: Défaut : actif. Un article obsolète encore utilisé par un abonnement doit être importé | K31: Non | R31: À traiter
A32: 27 | B32: So'Bloo | C32: Préférence de saisie de prix (Fiche article › Tarification › Dernier prix en …) | D32: transaction_price.is_input_with_tax_included | E32: Préférence de saisie de prix | F32: Liste | G32: HT / TTC | H32: Non | I32: Oui | J32: Défaut : HT. Indique si le montant importé est HT ou TTC. | R32: À traiter
A33: 28 | B33: So'Bloo | C33: Dépôt de garantie (Fiche article › Tarification › Dernier prix en abonnement, bouton d'ajout) | D33: variant.deposit_price_value + variant.deposit_price_currency | E33: Dépôt de garantie | F33: Montant | H33: Non | I33: Oui | J33: Uniquement avec un prix Abonnement. Utile pour le matériel loué (box, décodeur). | R33: À traiter
A34: 29 | B34: So'Bloo | C34: Plafond de réduction (Fiche article › Tarification › Dernier prix en …) | D34: transaction_price.maximum_discount | E34: Plafond de réduction | F34: Pourcentage | H34: Non | I34: Non | R34: À traiter
A35: 30 | B35: So'Bloo | C35: Prix par site de stockage / Ajouter un site (Fiche article › Tarification › Dernier prix en vente ; si prix par site activé) | D35: transaction_price.warehouse_id | E35: Prix par site de stockage | F35: Code de référence | H35: Non | I35: Oui | J35: Vide = prix par défaut | R35: À traiter
A36: 31 | B36: So'Bloo | C36: Code article fournisseur (Fiche article › Fournisseurs › Ajouter un article fournisseur) | D36: variant_supplier.code | E36: Code article fournisseur | F36: Texte | H36: Non | I36: Oui | J36: Obligatoire si un fournisseur est renseigné | R36: À traiter
A37: 32 | B37: So'Bloo | C37: Désignation fournisseur (Fiche article › Fournisseurs › Ajouter un article fournisseur) | D37: variant_supplier.label | E37: Désignation fournisseur | F37: Texte | H37: Non | I37: Oui | J37: Obligatoire si un fournisseur est renseigné (défaut : désignation de l'article) | R37: À traiter
A38: 33 | B38: So'Bloo | C38: Marque (Fiche article › Informations principales › Principales ; articles Physiques, si marques activées) | D38: article.brand_id | E38: Marque | F38: Code de référence | H38: Non | I38: Non | R38: À traiter
A39: 34 | B39: So'Bloo | C39: Code-barres associés (Fiche article › Informations principales ; articles Physiques) | D39: variant_barcodes.barcode (variant_barcodes.variant_id) | E39: Code-barres | F39: Texte | H39: Non | I39: Oui | J39: Plusieurs valeurs possibles | R39: À traiter
A40: 35 | B40: So'Bloo | C40: Commentaire interne (Fiche article › Informations principales › Principales) | D40: variant.comment | E40: Commentaire interne | F40: Texte | H40: Non | I40: Non | R40: À traiter
A41: 36 | B41: So'Bloo | C41: Disponiblité de l’article (Fiche article › Informations principales) | D41: article.is_option_only | E41: Disponibilité de l'article | F41: Liste | G41: Cet article est disponible en tant qu'article principal / Cet article est seulement disponible en tant qu'option | H41: Non | I41: Oui | J41: Défaut : article principal. Colonne NOT NULL sans défaut JPA : l'import doit envoyer false. | R41: À traiter
A42: 37 | B42: So'Bloo | C42: Quantité du lot par défaut (Fiche article › Informations principales ; si suivi par lot) | D42: variant.default_lot_size | E42: Quantité minimale de lot par défaut | F42: Nombre | H42: Non | I42: Oui | J42: Uniquement si suivi par lot | R42: À traiter
A43: 38 | B43: Smile | C43: À créer : Frais fixes associés | D43: À créer | E43: Frais ajoutés automatiquement à la souscription | F43: Code de référence | I43: Oui | J43: À vérifier d'abord : l'onglet « Packages associés » ou le type d'article Frais couvrent peut-être le besoin. Ex. frais de mise en service ajoutés à la création du contrat. Règle à décrire par Lagoon | K43: FMES | R43: À traiter
A44: 39 | B44: Smile | C44: À créer : Durée d'engagement minimum (mois) | D44: À créer | E44: Engagement en mois | F44: Nombre | I44: Oui | J44: À définir. Produits pros : pénalités si résiliation anticipée. Informatif pour les autres | K44: 24 | R44: À traiter
A45: 40 | B45: Smile | C45: À créer : Reconduction tacite | D45: À créer | E45: Reconduction par défaut | F45: Oui/Non | I45: Oui | J45: Défaut : Oui (atelier 17). Activée par défaut (atelier 17) | K45: Oui | R45: À traiter
A46: 41 | B46: Smile | C46: À créer : Mention « inclus » / « offert » sur facture | D46: À créer | E46: Affichage sur facture | F46: Liste | G46: Inclus / Offert | I46: Oui | J46: Liste plutôt que Oui/Non : Inclus / Offert / aucune mention | R46: À traiter
A47: 42 | B47: Smile | C47: À créer : Contrat requis | D47: À créer | E47: L'article génère un contrat | F47: Oui/Non | I47: Oui | J47: Ne pas confondre avec l'onglet « Contrats » de la fiche article, qui est un contrat tarifaire client. Notion de contrat paramétrable par produit | R47: À traiter
B48: Smile
B49: Smile
B50: Smile
B51: Smile
B52: Smile
B53: Smile
B54: Smile
B55: Smile
B56: Smile
B57: Smile
B58: Smile
B59: Smile
... B62: Smile

Sheet 5-Réductions
A1: Réductions
A2: Fichier dédié, importé après les articles. Absentes des données actuelles : à fournir par Lagoon. Aucun import de réductions n'existe aujourd'hui.
B4: SO'BLOO — pré-rempli | L4: LAGOON — à compléter | R4: SUIVI COMMUN
A5: N° | B5: Origine | C5: Libellé So'Bloo (écran) | D5: Champ en base (tech) | E5: Description | F5: Format | G5: Valeurs possibles | H5: Obligatoire dans So'Bloo | I5: Règle métier So'Bloo | J5: Détail de la règle So'Bloo | K5: Exemple | L5: Champ Smile correspondant | M5: Champ à reprendre ? | N5: Obligatoire pour Lagoon | O5: Règle métier Lagoon | P5: Détail de la règle Lagoon | Q5: Exemple réel (ID Smile) | R5: Statut | S5: Commentaires
A6: 1 | B6: So'Bloo | C6: Code de la réduction (ID Smile) (non affiché à l'écran) | D6: discount.code | E6: Code unique de la réduction | F6: Code de référence | H6: Oui | I6: Oui | J6: Non affiché à l'écran. Un code renseigné classe la réduction en « code promo » (usage unique) : clé de rapprochement à porter autrement (à définir). Non unique en base | K6: RED-EMPLOYE | R6: À traiter
A7: 2 | B7: So'Bloo | C7: Nom de la réduction (Ventes › Réductions › fiche réduction) | D7: discount.label | E7: Nom de la réduction | F7: Texte | H7: Non | I7: Non | J7: Exigé à l'écran | K7: Remise employé | R7: À traiter
A8: 3 | B8: So'Bloo | C8: État (liste des Réductions ; actions « Valider cette promotion » / « Passer en brouillon ») | D8: discount.state | E8: Brouillon / Validée / Supprimée | F8: Liste | G8: Brouillon / Validée / Supprimée | H8: Non | I8: Oui | J8: Défaut : Brouillon (importer en Validée). Seules les réductions Validées s'appliquent : importer en Validée | K8: Validée | R8: À traiter
A9: 4 | B9: So'Bloo | C9: Applicable (fiche réduction, affiché seulement pour une réduction en Montant) | D9: discount.type | E9: Remise unitaire ou sur le total | F9: Liste | G9: Sur le prix de l'unité / Sur le total | H9: Non | I9: Oui | J9: Défaut : Sur le prix de l'unité | K9: Unitaire | R9: À traiter
A10: 5 | B10: So'Bloo | C10: Pourcentage de réduction (fiche réduction, Type de réduction = Pourcentage) | D10: discount_step.percentage | E10: Pourcentage de réduction | F10: Pourcentage | H10: Non | I10: Oui | J10: Obligatoire : pourcentage OU montant. Au moins un palier, avec un % > 0 ou un montant > 0 (le % prime si les deux) | K10: 100 % | R10: À traiter
A11: 6 | B11: So'Bloo | C11: Montant HT de réduction (fiche réduction, Type de réduction = Montant) | D11: discount_step.amount (+ discount_step.currency) | E11: Montant HT de réduction | F11: Montant | H11: Non | I11: Oui | J11: Obligatoire : pourcentage OU montant | R11: À traiter
A12: 7 | B12: So'Bloo | C12: À partir de (paliers, si « Avec dégressivité » = Oui) | D12: discount_step.quantity_threshold | E12: Palier de quantité | F12: Nombre | H12: Non | I12: Oui | J12: Défaut : 1. Le palier retenu est le plus haut seuil ≤ quantité | K12: 1 | R12: À traiter
A13: 8 | B13: So'Bloo | C13: Débute le (fiche réduction) | D13: discount.start_date | E13: Début de validité | F13: Date | H13: Non | I13: Oui | J13: Exigée à l'écran ; côté serveur, obligatoire si date de fin ou remise sans cible. Obligatoire si une date de fin est saisie, ou pour une remise sans cible | R13: À traiter
A14: 9 | B14: So'Bloo | C14: Termine le (fiche réduction) | D14: discount.end_date | E14: Fin de validité | F14: Date | H14: Non | I14: Oui | J14: ≥ date de début. Ex. premiers mois d'abonnement | R14: À traiter
A15: 10 | B15: So'Bloo | C15: Clients (fiche réduction, choix « Une sélection de clients ») | D15: discount_customer.customer_id | E15: Remise propre à un client | F15: Code de référence | H15: Non | I15: Oui | J15: S'applique aussi aux établissements enfants | R15: À traiter
A16: 11 | B16: So'Bloo | C16: Groupes clients (fiche réduction, « Une sélection de clients et de groupes de clients ») | D16: discount_customer_group.customer_group_id | E16: Remise par groupe (CE, employé…) | F16: Code de référence | H16: Non | I16: Oui | J16: Les groupes doivent exister | K16: EMPLOYE | R16: À traiter
A17: 12 | B17: So'Bloo | C17: Articles (fiche réduction, « Une sélection d'articles ») | D17: discount_variant.variant_id | E17: Remise sur des articles | F17: Code de référence | H17: Non | I17: Oui | J17: Chaque article doit exister (onglets 3 et 4) | K17: ALTO-PLUS | R17: À traiter
A18: 13 | B18: So'Bloo | C18: Marque (fiche réduction, « Une marque, une famille ») | D18: discount_brand_tag.brand_id | E18: Marque concernée | F18: Code de référence | H18: Non | I18: Oui | J18: Sans aucune cible : remise globale (une seule sans période par client ou article) | R18: À traiter
A19: 14 | B19: So'Bloo | C19: Famille (fiche réduction, « Une marque, une famille ») | D19: discount_brand_tag.tag_id | E19: Famille concernée | F19: Code de référence | H19: Non | I19: Oui | R19: À traiter
A20: 15 | B20: So'Bloo | C20: Règle de cumul (information) (non affiché à l'écran) | D20: Sans objet (règle du moteur de prix) | E20: Règle d'application | F20: Texte | H20: Non | I20: Oui | J20: Les remises NE SE CUMULENT PAS : So'bloo retient le prix le plus bas (contrat tarifaire prioritaire). Pas de remise automatique sur les articles de type Service | R20: À traiter
A21: 16 | B21: So'Bloo | C21: Compte comptable de remise (information) (non affiché à l'écran) | D21: Sans objet (compte Remise de la famille d'article ou compte par défaut) | E21: Compte comptable | F21: Code de référence | H21: Non | I21: Oui | J21: Pas de compte sur la réduction : il vient de la famille de l'article ou du compte Remise par défaut | R21: À traiter
A22: 17 | B22: So'Bloo | C22: Organisation (non affiché à l'écran) | D22: discount.organization_id | E22: Organisation | F22: Liste | G22: Lagoon / Lagoon Business | H22: Oui | I22: Oui | R22: À traiter
A23: 18 | B23: Smile | C23: À créer : Portée : article seul ou article + options | D23: À créer | E23: Validé en atelier 14 (employé = 100 % article et options) | F23: Liste | I23: Oui | J23: À vérifier dans le moteur actuel | R23: À traiter
A24: 19 | B24: Smile | C24: À créer : Réduction sur package (Alto+ et options) | D24: À créer | E24: Remise globale ou option « toutes options » | F24: Liste | I24: Oui | J24: À arbitrer ensemble (atelier 14) | R24: À traiter
B25: Smile
B26: Smile
B27: Smile
B28: Smile
B29: Smile
B30: Smile
B31: Smile
B32: Smile
B33: Smile
B34: Smile
B35: Smile
B36: Smile
... B39: Smile

Sheet 6-Abonnements
A1: Abonnements
A2: En cours uniquement, sans historique des factures. Dans So'bloo, un abonnement est un devis de type Abonnement avec ses lignes et son plan de facturation. Aucun import d'abonnements n'existe aujourd'hui.
B4: SO'BLOO — pré-rempli | L4: LAGOON — à compléter | R4: SUIVI COMMUN
A5: N° | B5: Origine | C5: Libellé So'Bloo (écran) | D5: Champ en base (tech) | E5: Description | F5: Format | G5: Valeurs possibles | H5: Obligatoire dans So'Bloo | I5: Règle métier So'Bloo | J5: Détail de la règle So'Bloo | K5: Exemple | L5: Champ Smile correspondant | M5: Champ à reprendre ? | N5: Obligatoire pour Lagoon | O5: Règle métier Lagoon | P5: Détail de la règle Lagoon | Q5: Exemple réel (ID Smile) | R5: Statut | S5: Commentaires
A6: 1 | B6: So'Bloo | C6: Numéro de marché (Abonnement › Informations supplémentaires) | D6: estimate.contract_number | E6: Numéro de marché de l'abonnement | F6: Code de référence | H6: Non | I6: Oui | J6: Ne pas y stocker l'ID Smile : le champ est visible et modifiable à l'écran. L'identifiant du contrat Smile est porté par le contrat d'abonnement (subscription_contract, voir plus bas) | R6: À traiter
A7: 2 | B7: So'Bloo | C7: Client (Abonnement) | D7: estimate.customer_id | E7: Client titulaire | F7: Code de référence | H7: Oui | I7: Oui | J7: Le client doit exister (onglet 2), sinon ligne rejetée | K7: 100001 | R7: À traiter
A8: 3 | B8: So'Bloo | C8: Établissement (colonne de la grille des lignes, si affichée ; « Modifier l'établissement ») | D8: estimate_line.customer_id | E8: Établissement du client par ligne | F8: Code de référence | H8: Non | I8: Oui | J8: Défaut : client de l'abonnement. Client enfant (établissement) ; recopié sur les commandes | R8: À traiter
A9: 4 | B9: So'Bloo | C9: État (liste des abonnements) ; badge en cours / inactif / Suspendu / Partiellement suspendu / Résilié | D9: estimate.state | E9: Validé / Suspendu / Partiellement suspendu | F9: Liste | G9: Validé / Suspendu / Partiellement suspendu | H9: Oui | I9: Oui | J9: Abonnements en cours = Validé. Un abonnement suspendu ne génère pas de commande. « Résilié » n'est pas un statut : il se déduit d'une date de fin passée | K9: Validé | R9: À traiter
A10: 5 | B10: So'Bloo | C10: Organisation (non affiché à l'écran) | D10: estimate.organization_id | E10: Lagoon / Lagoon Business | F10: Liste | G10: Lagoon / Lagoon Business | H10: Oui | I10: Oui | J10: Visible pour l'organisation définie | K10: Lagoon | R10: À traiter
A11: 6 | B11: So'Bloo | C11: Article (grille des lignes de l'abonnement) | D11: estimate_line.variant_id | E11: Code de l'article souscrit | F11: Code de référence | H11: Oui | I11: Oui | J11: Une ligne par article. Doit exister (onglet 4) | K11: ALTO-PLUS | R11: À traiter
A12: 7 | B12: So'Bloo | C12: Ajuster les options (tiroir d'options de la ligne) | D12: estimate_line.option_id (ligne enfant, estimate_line.parent_id) | E12: Options souscrites | F12: Code de référence | H12: Non | I12: Oui | J12: Une option est une ligne enfant de la ligne article (ligne parente + option). L'option doit être rattachée à l'article (onglet 4) | K12: OPT-IP-FIXE | R12: À traiter
A13: 8 | B13: So'Bloo | C13: « en abonnement » sous le prix de la ligne (non saisissable) | D13: estimate_line.transaction_type | E13: Vente, abonnement ou package | F13: Liste | G13: Vente / Abonnement / Package | H13: Non | I13: Oui | J13: Défaut : type du prix de transaction de l'article. Abonnement pour les lignes récurrentes | K13: Abonnement | R13: À traiter
A14: 9 | B14: So'Bloo | C14: Quantité (grille des lignes) | D14: estimate_line.quantity | E14: Quantité souscrite | F14: Nombre | H14: Non | I14: Oui | J14: Défaut : 1. Strictement positive | K14: 1 | R14: À traiter
A15: 10 | B15: So'Bloo | C15: Prix unitaire HT (non affiché à l'écran) | D15: estimate_line.price_value (+ price_currency) | E15: Prix HT de la ligne | F15: Montant | H15: Non | I15: Oui | J15: Défaut : prix catalogue de l'article. ≥ 0. Prix négocié possible (sinon prix catalogue) | K15: 5000 | R15: À traiter
A16: 11 | B16: So'Bloo | C16: Remise (grille des lignes ; « Modifier la remise unitaire ») | D16: estimate_line.discount_percentage | E16: Remise en pourcentage | F16: Pourcentage | H16: Non | I16: Oui | J16: Plafond de remise par rôle et par article. Réduction en cours : reprendre la période restante | R16: À traiter
A17: 12 | B17: So'Bloo | C17: Remise (grille des lignes) | D17: estimate_line.discount_amount (+ discount_currency) | E17: Remise en montant | F17: Montant | H17: Non | I17: Oui | R17: À traiter
A18: 13 | B18: So'Bloo | C18: Débute en (période de la ligne) ; colonne « Date de début » | D18: estimate_line.start_date | E18: Début de la ligne | F18: Date | H18: Oui | I18: Oui | J18: INDISPENSABLE : une ligne sans date de début n'est jamais facturée. Les dates de l'abonnement sont calculées depuis les lignes | K18: 01/03/2024 | R18: À traiter
A19: 14 | B19: So'Bloo | C19: Termine en (période de la ligne) ; colonne « Date de fin actuelle » | D19: estimate_line.end_date | E19: Fin de la ligne | F19: Date | H19: Non | I19: Oui | J19: ≥ date de début | R19: À traiter
A20: 15 | B20: So'Bloo | C20: Date de renouvellement (badge RC / NC de la ligne ; « Modifier la date de renouvellement ? ») | D20: estimate_line.renewal_date | E20: Date anniversaire | F20: Date | H20: Non | I20: Oui | J20: Défaut : début de la 1re commande + 1 an. Si vide : début de la 1re commande + 1 an | R20: À traiter
A21: 16 | B21: So'Bloo | C21: Récurrence (liste des abonnements) ; « / mois » sous le prix de la ligne | D21: estimate_line.invoice_frequency_multiple + estimate_line.invoice_frequency_period | E21: Mensuel, trimestriel, annuel… | F21: Liste | G21: jour / semaine / mois / an (avec un multiple) | H21: Non | I21: Oui | J21: Défaut : périodicité du prix d'abonnement de l'article. Portée par chaque ligne d'abonnement, copiée du prix de l'article. Certains clients paient 12 mois d'avance | K21: 1 mois | R21: À traiter
A22: 17 | B22: So'Bloo | C22: Type de période (filtre de la liste) ; affiché dans l'en-tête de l'abonnement | D22: invoice_plan.invoicing_period | E22: Échu ou à échoir | F22: Liste | G22: Période consommée / Période à consommer | H22: Non | I22: Oui | J22: Défaut : paramètre tenant « Période facturée », sinon Période à consommer | K22: À échoir | R22: À traiter
A23: 18 | B23: So'Bloo | C23: Date de première facturation (Conditions de facturation des prestations hors abonnement) | D23: invoice_plan.invoicing_start_date | E23: Date de démarrage de la facturation | F23: Date | H23: Non | I23: Oui | J23: Concerne les prestations hors abonnement (plan de facturation) : sans objet pour la reprise des abonnements | R23: À traiter
A24: 19 | B24: So'Bloo | C24: Date de prochaine échéance (Smile) (non affiché à l'écran) | D24: Calculée (aucune colonne) | E24: Prochaine facturation | F24: Date | H24: Oui | I24: Oui | J24: Pas de champ stocké : So'bloo la calcule depuis la dernière période facturée. L'import doit la traduire en dates de début / de facturation pour éviter double facturation ou trou | K24: 01/11/2026 | R24: À traiter
A25: 20 | B25: So'Bloo | C25: Date limite de validité | D25: estimate.due_date / estimate.due_date_type | E25: Fin de période promo ou contractuelle | F25: Date | G25: fin de période promotionnelle / fin de période contractuelle / hors période promotionnelle | H25: Non | I25: Oui | J25: Date limite de validité calculée automatiquement : ne s'importe pas. Aucun champ « fin d'engagement » dans So'Bloo | R25: À traiter
A26: 21 | B26: So'Bloo | C26: Souhaitez-vous télécharger le mandat de prélèvement … ? (Adresse et prélèvement › Autorisation de prélèvement) | D26: estimate.with_direct_debit | E26: Abonnement payé par prélèvement | F26: Oui/Non | H26: Non | I26: Oui | J26: Défaut : Non. Le mandat doit être Validé sur le client | K26: Oui | R26: À traiter
A27: 22 | B27: So'Bloo | C27: Ligne ou Véhicule selon le paramétrage (colonne de la grille des lignes) | D27: estimate_line.equipment_id | E27: Matériel associé (exemplaire) | F27: Code de référence | H27: Non | I27: Oui | J27: Exemplaire de l'article (matériel) ; son n° de série est le code-barres de l'exemplaire. Un seul abonnement par exemplaire | R27: À traiter
A28: 23 | B28: So'Bloo | C28: Libellé propre à chaque propriété (colonnes paramétrables de la liste des abonnements et des lignes) | D28: estimate_attribute.value / estimate_line_attribute.value (+ tables *_attribute_value pour les listes) | E28: Champs personnalisés de l'abonnement et des lignes | F28: Texte | H28: Non | I28: Oui | J28: Obligation paramétrable par propriété. Définies globalement, PAS par type d'abonnement : onglets 6a / 6b à traduire en propriétés. Ni import ni contrôle serveur aujourd'hui | R28: À traiter
A29: 24 | B29: So'Bloo | C29: Libellé de l'abonnement (Abonnement › Détails) | D29: estimate.label | E29: Libellé de l'abonnement | F29: Texte | H29: Non | I29: Oui | R29: À traiter
A30: 25 | B30: So'Bloo | C30: Contrat d'abonnement › Référence | D30: subscription_contract.ref | E30: Référence du contrat signé par le client | F30: Code de référence | H30: Oui | I30: Oui | J30: Clé de rapprochement proposée : y porter l'identifiant du contrat Smile. Aujourd'hui générée par So'Bloo (référence de l'abonnement + « -n ») | K30: AB-000123-1 | R30: À traiter
A31: 26 | B31: So'Bloo | C31: Contrat d'abonnement › Abonnement | D31: subscription_contract.subscription_id | E31: Abonnement auquel le contrat est rattaché | F31: Code de référence | H31: Oui | I31: Oui | J31: Un abonnement peut avoir plusieurs contrats ; le dernier fait foi | R31: À traiter
A32: 27 | B32: So'Bloo | C32: Contrat d'abonnement › Libellé | D32: subscription_contract.label | E32: Libellé du contrat | F32: Texte | H32: Non | I32: Non | R32: À traiter
A33: 28 | B33: So'Bloo | C33: Contrat d'abonnement › Fichier | D33: subscription_contract.filename / subscription_contract.original_file_name | E33: PDF du contrat | F33: Fichier | H33: Non | I33: Oui | J33: PDF généré par So'Bloo. Reprise du PDF signé dans Smile à décider | R33: À traiter
A34: 29 | B34: So'Bloo | C34: Contrat d'abonnement › Statut de signature | D34: subscription_contract.signature_status | E34: Statut de la signature du contrat | F34: Liste | G34: Non signé / En attente de signature / Signé / Rejeté / Annulé | H34: Oui | I34: Oui | J34: Défaut : Non signé | K34: Signé | R34: À traiter
A35: 30 | B35: So'Bloo | C35: Contrat d'abonnement › Date de signature | D35: subscription_contract.signature_date | E35: Date de signature par le client | F35: Date | H35: Non | I35: Oui | R35: À traiter
A36: 31 | B36: So'Bloo | C36: Contrat d'abonnement › Date du dernier envoi | D36: subscription_contract.last_sending_date | E36: Dernier envoi du contrat au client | F36: Date | H36: Non | I36: Non | R36: À traiter
A37: 32 | B37: Smile | C37: À créer : Type d'abonnement | D37: À créer | E37: Internet, VOIP, hébergement… | F37: Liste | G37: Internet / VOIP / Hébergement / … | I37: Oui | J37: N'existe pas dans So'bloo : à porter par la famille d'article ou une propriété | K37: Internet | R37: À traiter
A38: 33 | B38: Smile | C38: À créer : Centre de coût | D38: À créer | E38: Regroupement des abonnements par site sur facture | F38: Liste | I38: Oui | J38: Aucune entité centre de coût : piste = établissements (client parent / enfants) | R38: À traiter
B39: Smile
B40: Smile
B41: Smile
B42: Smile
B43: Smile
B44: Smile
B45: Smile
B46: Smile
B47: Smile
B48: Smile

Sheet 6a-Abo Internet
A1: Abonnements — propriétés Internet
A2: Propriétés dynamiques propres aux abonnements Internet. Dans So'bloo, à créer comme propriétés de ligne d'abonnement (types de champ : texte, mot de passe, téléphone, exemplaire…). Liste à compléter par Lagoon.
B4: SO'BLOO — pré-rempli | L4: LAGOON — à compléter | R4: SUIVI COMMUN
A5: N° | B5: Origine | C5: Libellé So'Bloo (écran) | D5: Champ en base (tech) | E5: Description | F5: Format | G5: Valeurs possibles | H5: Obligatoire dans So'Bloo | I5: Règle métier So'Bloo | J5: Détail de la règle So'Bloo | K5: Exemple | L5: Champ Smile correspondant | M5: Champ à reprendre ? | N5: Obligatoire pour Lagoon | O5: Règle métier Lagoon | P5: Détail de la règle Lagoon | Q5: Exemple réel (ID Smile) | R5: Statut | S5: Commentaires
A6: 1 | B6: So'Bloo | C6: Contrat d'abonnement › Référence | D6: subscription_contract.ref | E6: Lien vers l'onglet 6 | F6: Code de référence | H6: Oui | I6: Oui | J6: Doit exister dans l'onglet 6 | K6: AB-000123 | R6: À traiter
A7: 2 | B7: Smile | C7: À créer : Identifiant de connexion | D7: À créer | E7: Login du service | F7: Texte | I7: Oui | J7: Unique (propriété « valeur unique »). Lien Radius | R7: À traiter
A8: 3 | B8: Smile | C8: À créer : Mot de passe de connexion | D8: À créer | E8: Généré à la souscription | F8: Texte | I8: Oui | J8: Type de propriété « Mot de passe » disponible ; stockage à vérifier (chiffrement). Mode de reprise à définir | R8: À traiter
A9: 4 | B9: Smile | C9: À créer : Numéro de ligne OPT | D9: À créer | E9: Ligne OPT support de l'option Internet | F9: Téléphone | I9: Oui | R9: À traiter
A10: 5 | B10: Smile | C10: À créer : N° de série du matériel | D10: À créer | E10: Modem, routeur | F10: Texte | I10: Oui | J10: Existe déjà : code-barres de l'exemplaire (matériel suivi par exemplaire) | R10: À traiter
A11: 6 | B11: Smile | C11: À créer : Adresse MAC | D11: À créer | E11: Matériel associé | F11: Texte | I11: Oui | J11: Existe déjà sur l'exemplaire : adresse MAC unique, format contrôlé, obligation paramétrable. Critère de recherche des abonnements | R11: À traiter
B12: Smile
B13: Smile
B14: Smile
B15: Smile
B16: Smile
B17: Smile
B18: Smile
B19: Smile
B20: Smile
B21: Smile
B22: Smile
B23: Smile
... B26: Smile

Sheet 6b-Abo VOIP
A1: Abonnements — propriétés VOIP
A2: Propriétés dynamiques propres aux abonnements VOIP. Liste à compléter par Lagoon.
B4: SO'BLOO — pré-rempli | L4: LAGOON — à compléter | R4: SUIVI COMMUN
A5: N° | B5: Origine | C5: Libellé So'Bloo (écran) | D5: Champ en base (tech) | E5: Description | F5: Format | G5: Valeurs possibles | H5: Obligatoire dans So'Bloo | I5: Règle métier So'Bloo | J5: Détail de la règle So'Bloo | K5: Exemple | L5: Champ Smile correspondant | M5: Champ à reprendre ? | N5: Obligatoire pour Lagoon | O5: Règle métier Lagoon | P5: Détail de la règle Lagoon | Q5: Exemple réel (ID Smile) | R5: Statut | S5: Commentaires
A6: 1 | B6: So'Bloo | C6: Contrat d'abonnement › Référence | D6: subscription_contract.ref | E6: Lien vers l'onglet 6 | F6: Code de référence | H6: Oui | I6: Oui | J6: Doit exister dans l'onglet 6 | R6: À traiter
A7: 2 | B7: Smile | C7: À créer : Numéro VOIP | D7: À créer | E7: Numéro attribué | F7: Téléphone | I7: Oui | J7: À décrire par Lagoon | R7: À traiter
A8: 3 | B8: Smile | C8: À créer : (à compléter par Lagoon) | D8: À créer | F8: Texte | I8: Non | R8: À traiter
B9: Smile
B10: Smile
B11: Smile
B12: Smile
B13: Smile
B14: Smile
B15: Smile
B16: Smile
B17: Smile
B18: Smile
B19: Smile
B20: Smile
... B23: Smile

Sheet Cas limites
A1: Cas limites et cas spécifiques
A2: Particularités du SI ou des pratiques de Lagoon, invisibles depuis les fichiers. Lagoon répond, la règle d'import est fixée ensemble.
A5: N° | B5: Lot | C5: Cas à vérifier | D5: Risque si non anticipé | E5: Réponse Lagoon | F5: Exemple réel (ID Smile) | G5: Règle d'import retenue | H5: Statut
A6: 1 | B6: Clients | C6: Les clients (pro et particuliers) sont-ils répartis sur plusieurs bases ou outils ? L'extract les couvre-t-il tous ? | D6: Clients manquants, comme lors de l'import SEPA (clients pros sur deux bases) | H6: À traiter
A7: 2 | B7: Clients | C7: Existe-t-il des clients sans référence Smile ? Comment les identifier ? | D7: Ligne rejetée : la référence Smile est la clé primaire | H7: À traiter
A8: 3 | B8: Clients | C8: Un même client peut-il exister sous plusieurs identifiants Smile ? | D8: Doublons, facturation dispersée | H8: À traiter
A9: 4 | B9: Clients | C9: Un client peut-il changer de type (particulier ↔ pro) ou cumuler les deux ? | D9: Mauvais type, mauvaise imputation comptable | H9: À traiter
A10: 5 | B10: Clients | C10: Faut-il reprendre les clients résiliés ou inactifs, et depuis quand ? | D10: Volume inutile, ou historique manquant pour le support | H10: À traiter
A11: 6 | B11: Clients | C11: Adresse de facturation différente de l'adresse d'installation, ou adresses multiples ? | D11: Factures ou interventions à la mauvaise adresse | H11: À traiter
A12: 7 | B12: Clients | C12: Payeur différent du titulaire (groupe, maison mère, tiers payeur) ? | D12: Factures adressées au mauvais tiers | H12: À traiter
A13: 8 | B13: Options et articles | C13: Une option peut-elle être partagée par plusieurs articles ? | D13: Option dupliquée ou mal rattachée | H13: À traiter
A14: 9 | B14: Options et articles | C14: Lagoon utilisera-t-elle les variantes d'articles ? | D14: Structure du catalogue à revoir après import | H14: À traiter
A15: 10 | B15: Options et articles | C15: Un article a-t-il une ventilation comptable sur plusieurs comptes ? | D15: Écritures comptables fausses | H15: À traiter
A16: 11 | B16: Options et articles | C16: Existe-t-il des articles obsolètes encore présents sur des abonnements en cours ? | D16: Abonnement rejeté faute d'article | H16: À traiter
A17: 12 | B17: Options et articles | C17: Des prix diffèrent-ils selon le type de client ou la zone ? | D17: Mauvais tarif appliqué | H17: À traiter
... A19: 14 | B19: Réductions | C19: Des réductions sont-elles en cours sur des abonnements actifs ? Avec quelle période restante ? | D19: Avantage client perdu ou prolongé à la bascule | H19: À traiter
A20: 15 | B20: Abonnements | C20: Reprise des seuls abonnements en cours, sans historique des factures ? | D20: Impossible de répondre sur une facture ancienne | E20: À priori oui, à valider | H20: En discussion
A21: 16 | B21: Abonnements | C21: Abonnements suspendus, en préavis ou en cours de résiliation : les reprend-on, avec quel état ? | D21: Réactivation ou facturation à tort | H21: À traiter
A22: 17 | B22: Abonnements | C22: Factures en cours ou période partiellement facturée à la date de bascule ? | D22: Double facturation ou période non facturée | H22: À traiter
A23: 18 | B23: Abonnements | C23: Quels types d'abonnement portent des propriétés dynamiques (Internet, VOIP…) et lesquelles ? | D23: Données techniques perdues (login, MAC, n° de série) | H23: À traiter
A24: 19 | B24: Abonnements | C24: Un abonnement peut-il porter sur plusieurs sites ou plusieurs payeurs ? | D24: Abonnement rejeté ou mal ventilé | H24: À traiter
A25: 20 | B25: Comptabilité | C25: Comment les types de clients sont-ils traités en comptabilité ? | D25: Écritures sur les mauvais comptes | E25: Tous les clients en débit | H25: En discussion
A26: 21 | B26: Comptabilité | C26: Quelles catégories de rapports de vente (sales report categories) utilisez-vous ? | D26: Reporting des ventes incomparable avant / après | H26: À traiter
A27: 22 | B27: Comptabilité | C27: Existe-t-il un workflow de recouvrement à reprendre ? | D27: Relances interrompues, impayés non suivis | E27: À priori non ; statut client (contentieux…) à reprendre | H27: En discussion
A28: 23 | B28: Comptabilité | C28: Soldes, impayés, avoirs ou dépôts de garantie en cours à la date de bascule ? | D28: Dettes ou crédits clients perdus | H28: À traiter
A29: 24 | B29: Sources et volumétrie | C29: Liste exhaustive des bases, instances et outils où vivent les données (Smile et hors Smile) | D29: Données manquantes découvertes en production | H29: À traiter
A30: 25 | B30: Sources et volumétrie | C30: Volumes attendus par import (clients, articles, options, réductions, abonnements) | D30: Imports trop longs, contrôle de comptage impossible | H30: À traiter
A31: 26 | B31: Sources et volumétrie | C31: Encodage, séparateurs, formats de dates et de montants des extracts | D31: Caractères accentués ou montants corrompus | H31: À traiter
A32: 27 | B32: Sources et volumétrie | C32: Les données Smile évolueront-elles entre l'extraction finale et la bascule ? | D32: Écarts entre Smile et Sobloo au démarrage | H32: À traiter
